{
  "Siri": {
    "ServiceDelivery": {
      "VehicleMonitoringDelivery": [
        {
          "VehicleActivity": [
            {
              "MonitoredVehicleJourney": {
                "LineRef": "MTA NYCT_M15",
                "DirectionRef": "1",
                "FramedVehicleJourneyRef": {
                  "DataFrameRef": "2025-04-01",
                  "DatedVehicleJourneyRef": "MTA NYCT_OH_B5-Weekday-SDon-026000_M15_207"
                },
                "PublishedLineName": [
                  "M15"
                ],
                "DestinationRef": "MTA_803002",
                "DestinationName": [
                  "SOUTH FERRY via 2 AV"
                ],
                "OriginAimedDepartureTime": "2025-04-01T04:20:00.000-04:00",
                "SituationRef": [
                  {
                    "SituationSimpleRef": "MTA NYCT_lmm:alert:420753"
                  },
                  {
                    "SituationSimpleRef": "MTA NYCT_lmm:planned_work:10129"
                  },
                  {
                    "SituationSimpleRef": "MTA NYCT_lmm:planned_work:21502"
                  }
                ],
                "Monitored": true,
                "VehicleLocation": {
                  "Longitude": -73.932605,
                  "Latitude": 40.803232
                },
                "Bearing": 157.34065,
                "ProgressRate": "noProgress",
                "ProgressStatus": [
                  "layover"
                ],
                "VehicleRef": "MTA NYCT_5339",
                "MonitoredCall": {
                  "AimedArrivalTime": "2025-04-01T04:20:55.007-04:00",
                  "ExpectedArrivalTime": "2025-04-01T04:13:28.504-04:00",
                  "ArrivalProximityText": "< 1 stop away",
                  "ExpectedDepartureTime": "2025-04-01T04:13:28.504-04:00",
                  "DistanceFromStop": 201,
                  "NumberOfStopsAway": 0,
                  "VisitNumber": 1,
                  "StopPointName": [
                    "2 AV/E 124 ST"
                  ]
                }
              },
              "RecordedAtTime": "2025-04-01T04:12:52.000-04:00"
            },
            {
              "MonitoredVehicleJourney": {
                "LineRef": "MTA NYCT_M42",
                "DirectionRef": "0",
                "FramedVehicleJourneyRef": {
                  "DataFrameRef": "2025-04-01",
                  "DatedVehicleJourneyRef": "MTA NYCT_MQ_B5-Weekday-SDon-024300_M42_301"
                },
                "PublishedLineName": [
                  "M42"
                ],
                "DestinationRef": "MTA_903046",
                "DestinationName": [
                  "EAST SIDE U N-1 AV CROSSTOWN"
                ],
                "SituationRef": [
                  {
                    "SituationSimpleRef": "MTA NYCT_lmm:alert:420753"
                  }
                ],
                "Monitored": true,
                "VehicleLocation": {
                  "Longitude": -73.983332,
                  "Latitude": 40.754519
                },
                "Bearing": 337.15607,
                "ProgressRate": "normalProgress",
                "VehicleRef": "MTA NYCT_9717",
                "MonitoredCall": {
                  "AimedArrivalTime": "2025-04-01T04:13:23.015-04:00",
                  "ExpectedArrivalTime": "2025-04-01T04:13:58.778-04:00",
                  "ArrivalProximityText": "< 1 stop away",
                  "ExpectedDepartureTime": "2025-04-01T04:13:58.778-04:00",
                  "DistanceFromStop": 254,
                  "NumberOfStopsAway": 0,
                  "Extensions": {
                    "Capacities": {
                      "EstimatedPassengerCount": 4,
                      "EstimatedPassengerCapacity": 80
                    }
                  },
                  "VisitNumber": 1,
                  "StopPointName": [
                    "W 42 ST/5 AV"
                  ]
                }
              },
              "RecordedAtTime": "2025-04-01T04:13:02.079-04:00"
            },
            {
              "MonitoredVehicleJourney": {
                "LineRef": "MTA NYCT_M15",
                "DirectionRef": "1",
                "FramedVehicleJourneyRef": {
                  "DataFrameRef": "2025-04-01",
                  "DatedVehicleJourneyRef": "MTA NYCT_OH_B5-Weekday-SDon-021000_M15_204"
                },
                "PublishedLineName": [
                  "M15"
                ],
                "DestinationRef": "MTA_803002",
                "DestinationName": [
                  "SOUTH FERRY via 2 AV"
                ],
                "SituationRef": [
                  {
                    "SituationSimpleRef": "MTA NYCT_lmm:alert:420753"
                  },
                  {
                    "SituationSimpleRef": "MTA NYCT_lmm:planned_work:10129"
                  },
                  {
                    "SituationSimpleRef": "MTA NYCT_lmm:planned_work:21502"
                  }
                ],
                "Monitored": true,
                "VehicleLocation": {
                  "Longitude": -74.006539,
                  "Latitude": 40.705764
                },
                "Bearing": 215.31122,
                "ProgressRate": "normalProgress",
                "VehicleRef": "MTA NYCT_5359",
                "MonitoredCall": {
                  "AimedArrivalTime": "2025-04-01T04:14:46.019-04:00",
                  "ExpectedArrivalTime": "2025-04-01T04:13:35.686-04:00",
                  "ArrivalProximityText": "< 1 stop away",
                  "ExpectedDepartureTime": "2025-04-01T04:13:35.686-04:00",
                  "DistanceFromStop": 191,
                  "NumberOfStopsAway": 0,
                  "VisitNumber": 1,
                  "StopPointName": [
                    "WATER ST/GOUVERNEUR LN"
                  ]
                }
              },
              "RecordedAtTime": "2025-04-01T04:12:58.000-04:00"
            },
            {
              "MonitoredVehicleJourney": {
                "LineRef": "MTA NYCT_M103",
                "DirectionRef": "0",
                "FramedVehicleJourneyRef": {
                  "DataFrameRef": "2025-04-01",
                  "DatedVehicleJourneyRef": "MTA NYCT_OH_B5-Weekday-SDon-022200_M101_7"
                },
                "PublishedLineName": [
                  "M103"
                ],
                "DestinationRef": "MTA_903042",
                "DestinationName": [
                  "EAST HARLEM 125 ST via 3 AV"
                ],
                "SituationRef": [
                  {
                    "SituationSimpleRef": "MTA NYCT_lmm:alert:420753"
                  },
                  {
                    "SituationSimpleRef": "MTA NYCT_lmm:planned_work:21837"
                  },
                  {
                    "SituationSimpleRef": "MTA NYCT_lmm:planned_work:23451"
                  }
                ],
                "Monitored": true,
                "VehicleLocation": {
                  "Longitude": -73.944645,
                  "Latitude": 40.791595
                },
                "Bearing": 54.168343,
                "ProgressRate": "normalProgress",
                "VehicleRef": "MTA NYCT_5313",
                "MonitoredCall": {
                  "AimedArrivalTime": "2025-04-01T04:14:28.103-04:00",
                  "ExpectedArrivalTime": "2025-04-01T04:13:10.869-04:00",
                  "ArrivalProximityText": "approaching",
                  "ExpectedDepartureTime": "2025-04-01T04:13:10.869-04:00",
                  "DistanceFromStop": 40,
                  "NumberOfStopsAway": 0,
                  "VisitNumber": 1,
                  "StopPointName": [
                    "3 AV/E 106 ST"
                  ]
                }
              },
              "RecordedAtTime": "2025-04-01T04:12:56.000-04:00"
            },
            {
              "MonitoredVehicleJourney": {
                "LineRef": "MTA NYCT_M101",
                "DirectionRef": "0",
                "FramedVehicleJourneyRef": {
                  "DataFrameRef": "2025-04-01",
                  "DatedVehicleJourneyRef": "MTA NYCT_OH_B5-Weekday-SDon-021300_M101_3"
                },
                "PublishedLineName": [
                  "M101"
                ],
                "DestinationRef": "MTA_903360",
                "DestinationName": [
                  "FT GEORGE via 3 AV via AMSTERDAM AV"
                ],
                "SituationRef": [
                  {
                    "SituationSimpleRef": "MTA NYCT_lmm:alert:420753"
                  },
                  {
                    "SituationSimpleRef": "MTA NYCT_lmm:planned_work:21837"
                  },
                  {
                    "SituationSimpleRef": "MTA NYCT_lmm:planned_work:23451"
                  }
                ],
                "Monitored": true,
                "VehicleLocation": {
                  "Longitude": -73.951486,
                  "Latitude": 40.819906
                },
                "Bearing": 53.59909,
                "ProgressRate": "normalProgress",
                "VehicleRef": "MTA NYCT_5309",
                "MonitoredCall": {
                  "AimedArrivalTime": "2025-04-01T04:11:04.120-04:00",
                  "ExpectedArrivalTime": "2025-04-01T04:13:18.529-04:00",
                  "ArrivalProximityText": "approaching",
                  "ExpectedDepartureTime": "2025-04-01T04:13:18.529-04:00",
                  "DistanceFromStop": 147,
                  "NumberOfStopsAway": 0,
                  "VisitNumber": 1,
                  "StopPointName": [
                    "AMSTERDAM AV/W 138 ST"
                  ]
                }
              },
              "RecordedAtTime": "2025-04-01T04:12:55.000-04:00"
            },
            {
              "MonitoredVehicleJourney": {
                "LineRef": "MTA NYCT_M101",
                "DirectionRef": "1",
                "FramedVehicleJourneyRef": {
                  "DataFrameRef": "2025-04-01",
                  "DatedVehicleJourneyRef": "MTA NYCT_OH_B5-Weekday-SDon-025000_M101_2"
                },
                "PublishedLineName": [
                  "M101"
                ],
                "DestinationRef": "MTA_404092",
                "DestinationName": [
                  "EAST VILLAGE 3 AV-6 ST via LEX AV"
                ],
                "SituationRef": [
                  {
                    "SituationSimpleRef": "MTA NYCT_lmm:alert:420753"
                  },
                  {
                    "SituationSimpleRef": "MTA NYCT_lmm:planned_work:21837"
                  },
                  {
                    "SituationSimpleRef": "MTA NYCT_lmm:planned_work:23451"
                  }
                ],
                "Monitored": true,
                "VehicleLocation": {
                  "Longitude": -73.929153,
                  "Latitude": 40.854696
                },
                "Bearing": 337.0007,
                "ProgressRate": "normalProgress",
                "VehicleRef": "MTA NYCT_5302",
                "MonitoredCall": {
                  "AimedArrivalTime": "2025-04-01T04:12:03.128-04:00",
                  "ExpectedArrivalTime": "2025-04-01T04:13:27.053-04:00",
                  "ArrivalProximityText": "< 1 stop away",
                  "ExpectedDepartureTime": "2025-04-01T04:13:27.053-04:00",
                  "DistanceFromStop": 262,
                  "NumberOfStopsAway": 0,
                  "VisitNumber": 1,
                  "StopPointName": [
                    "AMSTERDAM AV/W 190 ST"
                  ]
                }
              },
              "RecordedAtTime": "2025-04-01T04:12:47.000-04:00"
            },
            {
              "MonitoredVehicleJourney": {
                "LineRef": "MTA NYCT_M60+",
                "DirectionRef": "0",
                "FramedVehicleJourneyRef": {
                  "DataFrameRef": "2025-04-01",
                  "DatedVehicleJourneyRef": "MTA NYCT_MQ_B5-Weekday-SDon-027700_SBS60_907"
                },
                "PublishedLineName": [
                  "M60-SBS"
                ],
                "DestinationRef": "MTA_804142",
                "DestinationName": [
                  "SELECT BUS LA GUARDIA AIRPORT"
                ],
                "OriginAimedDepartureTime": "2025-04-01T04:37:00.000-04:00",
                "SituationRef": [
                  {
                    "SituationSimpleRef": "MTA NYCT_lmm:alert:420753"
                  }
                ],
                "Monitored": true,
                "VehicleLocation": {
                  "Longitude": -73.967716,
                  "Latitude": 40.801821
                },
                "Bearing": 85.336655,
                "ProgressRate": "noProgress",
                "ProgressStatus": [
                  "layover"
                ],
                "VehicleRef": "MTA NYCT_5451",
                "MonitoredCall": {
                  "AimedArrivalTime": "2025-04-01T04:37:00.259-04:00",
                  "ArrivalProximityText": "at stop",
                  "DistanceFromStop": 0,
                  "NumberOfStopsAway": 0,
                  "VisitNumber": 1,
                  "StopPointName": [
                    "BROADWAY/W 106 ST"
                  ]
                }
              },
              "RecordedAtTime": "2025-04-01T04:12:48.000-04:00"
            },
            {
              "MonitoredVehicleJourney": {
                "LineRef": "MTA NYCT_M60+",
                "DirectionRef": "1",
                "FramedVehicleJourneyRef": {
                  "DataFrameRef": "2025-04-01",
                  "DatedVehicleJourneyRef": "MTA NYCT_MQ_B5-Weekday-SDon-022800_SBS60_901"
                },
                "PublishedLineName": [
                  "M60-SBS"
                ],
                "DestinationRef": "MTA_402018",
                "DestinationName": [
                  "SELECT BUS WEST SIDE BROADWAY-106 ST"
                ],
                "SituationRef": [
                  {
                    "SituationSimpleRef": "MTA NYCT_lmm:alert:420753"
                  }
                ],
                "Monitored": true,
                "VehicleLocation": {
                  "Longitude": -73.921473,
                  "Latitude": 40.797808
                },
                "Bearing": 165.96376,
                "ProgressRate": "normalProgress",
                "VehicleRef": "MTA NYCT_5454",
                "MonitoredCall": {
                  "AimedArrivalTime": "2025-04-01T04:16:29.263-04:00",
                  "ExpectedArrivalTime": "2025-04-01T04:14:37.559-04:00",
                  "ArrivalProximityText": "0.8 miles away",
                  "ExpectedDepartureTime": "2025-04-01T04:14:37.559-04:00",
                  "DistanceFromStop": 1222,
                  "NumberOfStopsAway": 0,
                  "VisitNumber": 1,
                  "StopPointName": [
                    "E 125 ST/2 AV"
                  ]
                }
              },
              "RecordedAtTime": "2025-04-01T04:12:42.000-04:00"
            },
            {
              "MonitoredVehicleJourney": {
                "LineRef": "MTA NYCT_M60+",
                "DirectionRef": "1",
                "FramedVehicleJourneyRef": {
                  "DataFrameRef": "2025-04-01",
                  "DatedVehicleJourneyRef": "MTA NYCT_MQ_B5-Weekday-SDon-020800_SBS60_904"
                },
                "PublishedLineName": [
                  "M60-SBS"
                ],
                "DestinationRef": "MTA_402018",
                "DestinationName": [
                  "SELECT BUS WEST SIDE BROADWAY-106 ST"
                ],
                "SituationRef": [
                  {
                    "SituationSimpleRef": "MTA NYCT_lmm:alert:420753"
                  }
                ],
                "Monitored": true,
                "VehicleLocation": {
                  "Longitude": -73.964641,
                  "Latitude": 40.807161
                },
                "Bearing": 233.70737,
                "ProgressRate": "normalProgress",
                "VehicleRef": "MTA NYCT_5445",
                "MonitoredCall": {
                  "AimedArrivalTime": "2025-04-01T04:05:00.273-04:00",
                  "ExpectedArrivalTime": "2025-04-01T04:14:10.778-04:00",
                  "ArrivalProximityText": "< 1 stop away",
                  "ExpectedDepartureTime": "2025-04-01T04:14:10.778-04:00",
                  "DistanceFromStop": 735,
                  "NumberOfStopsAway": 0,
                  "VisitNumber": 1,
                  "StopPointName": [
                    "W 106 ST/BROADWAY"
                  ]
                }
              },
              "RecordedAtTime": "2025-04-01T04:11:57.679-04:00"
            },
            {
              "MonitoredVehicleJourney": {
                "LineRef": "MTA NYCT_M60+",
                "DirectionRef": "0",
                "FramedVehicleJourneyRef": {
                  "DataFrameRef": "2025-04-01",
                  "DatedVehicleJourneyRef": "MTA NYCT_MQ_B5-Weekday-SDon-022500_SBS60_905"
                },
                "PublishedLineName": [
                  "M60-SBS"
                ],
                "DestinationRef": "MTA_804142",
                "DestinationName": [
                  "SELECT BUS LA GUARDIA AIRPORT"
                ],
                "SituationRef": [
                  {
                    "SituationSimpleRef": "MTA NYCT_lmm:alert:420753"
                  }
                ],
                "Monitored": true,
                "VehicleLocation": {
                  "Longitude": -73.910802,
                  "Latitude": 40.768832
                },
                "Bearing": 349.5464,
                "ProgressRate": "normalProgress",
                "VehicleRef": "MTA NYCT_5462",
                "MonitoredCall": {
                  "AimedArrivalTime": "2025-04-01T04:11:49.287-04:00",
                  "ExpectedArrivalTime": "2025-04-01T04:13:10.869-04:00",
                  "ArrivalProximityText": "at stop",
                  "ExpectedDepartureTime": "2025-04-01T04:13:10.869-04:00",
                  "DistanceFromStop": 0,
                  "NumberOfStopsAway": 0,
                  "VisitNumber": 1,
                  "StopPointName": [
                    "ASTORIA BLVD SOUTH/STEINWAY ST"
                  ]
                }
              },
              "RecordedAtTime": "2025-04-01T04:12:57.000-04:00"
            },
            {
              "MonitoredVehicleJourney": {
                "LineRef": "MTA NYCT_M60+",
                "DirectionRef": "0",
                "FramedVehicleJourneyRef": {
                  "DataFrameRef": "2025-04-01",
                  "DatedVehicleJourneyRef": "MTA NYCT_MQ_B5-Weekday-SDon-024000_SBS60_903"
                },
                "PublishedLineName": [
                  "M60-SBS"
                ],
                "DestinationRef": "MTA_804142",
                "DestinationName": [
                  "SELECT BUS LA GUARDIA AIRPORT"
                ],
                "SituationRef": [
                  {
                    "SituationSimpleRef": "MTA NYCT_lmm:alert:420753"
                  }
                ],
                "Monitored": true,
                "VehicleLocation": {
                  "Longitude": -73.94463,
                  "Latitude": 40.807419
                },
                "Bearing": 337.49017,
                "ProgressRate": "normalProgress",
                "VehicleRef": "MTA NYCT_5467",
                "MonitoredCall": {
                  "AimedArrivalTime": "2025-04-01T04:13:46.291-04:00",
                  "ExpectedArrivalTime": "2025-04-01T04:14:29.899-04:00",
                  "ArrivalProximityText": "< 1 stop away",
                  "ExpectedDepartureTime": "2025-04-01T04:14:29.899-04:00",
                  "DistanceFromStop": 422,
                  "NumberOfStopsAway": 0,
                  "VisitNumber": 1,
                  "StopPointName": [
                    "E 125 ST/MADISON AV"
                  ]
                }
              },
              "RecordedAtTime": "2025-04-01T04:12:51.000-04:00"
            },
            {
              "MonitoredVehicleJourney": {
                "LineRef": "MTA NYCT_M60+",
                "DirectionRef": "1",
                "FramedVehicleJourneyRef": {
                  "DataFrameRef": "2025-04-01",
                  "DatedVehicleJourneyRef": "MTA NYCT_MQ_B5-Weekday-SDon-024800_SBS60_902"
                },
                "PublishedLineName": [
                  "M60-SBS"
                ],
                "DestinationRef": "MTA_402018",
                "DestinationName": [
                  "SELECT BUS WEST SIDE BROADWAY-106 ST"
                ],
                "SituationRef": [
                  {
                    "SituationSimpleRef": "MTA NYCT_lmm:alert:420753"
                  }
                ],
                "Monitored": true,
                "VehicleLocation": {
                  "Longitude": -73.881854,
                  "Latitude": 40.769424
                },
                "Bearing": 209.57784,
                "ProgressRate": "normalProgress",
                "VehicleRef": "MTA NYCT_5466",
                "MonitoredCall": {
                  "AimedArrivalTime": "2025-04-01T04:15:59.295-04:00",
                  "ExpectedArrivalTime": "2025-04-01T04:15:56.960-04:00",
                  "ArrivalProximityText": "0.8 miles away",
                  "ExpectedDepartureTime": "2025-04-01T04:15:56.960-04:00",
                  "DistanceFromStop": 1236,
                  "NumberOfStopsAway": 0,
                  "VisitNumber": 1,
                  "StopPointName": [
                    "LGA/TERMINAL A - MARINE AIR TERMINAL"
                  ]
                }
              },
              "RecordedAtTime": "2025-04-01T04:13:00.000-04:00"
            },
            {
              "MonitoredVehicleJourney": {
                "LineRef": "MTA NYCT_M2",
                "DirectionRef": "0",
                "FramedVehicleJourneyRef": {
                  "DataFrameRef": "2025-04-01",
                  "DatedVehicleJourneyRef": "MTA NYCT_MV_B5-Weekday-SDon-019400_M2_202"
                },
                "PublishedLineName": [
                  "M2"
                ],
                "DestinationRef": "MTA_903049",
                "DestinationName": [
                  "WASHINGTON HTS BWAY-168 ST via MADISON"
                ],
                "SituationRef": [
                  {
                    "SituationSimpleRef": "MTA NYCT_lmm:alert:420753"
                  },
                  {
                    "SituationSimpleRef": "MTA NYCT_lmm:planned_work:22663"
                  },
                  {
                    "SituationSimpleRef": "MTA NYCT_lmm:planned_work:23502"
                  }
                ],
                "Monitored": true,
                "VehicleLocation": {
                  "Longitude": -73.938348,
                  "Latitude": 40.837863
                },
                "Bearing": 157.65523,
                "ProgressRate": "normalProgress",
                "VehicleRef": "MTA NYCT_9837",
                "MonitoredCall": {
                  "AimedArrivalTime": "2025-04-01T04:14:00.341-04:00",
                  "ExpectedArrivalTime": "2025-04-01T04:14:19.251-04:00",
                  "ArrivalProximityText": "< 1 stop away",
                  "ExpectedDepartureTime": "2025-04-01T04:14:19.251-04:00",
                  "DistanceFromStop": 417,
                  "NumberOfStopsAway": 0,
                  "Extensions": {
                    "Capacities": {
                      "EstimatedPassengerCount": 3,
                      "EstimatedPassengerCapacity": 80
                    }
                  },
                  "VisitNumber": 1,
                  "StopPointName": [
                    "W 168 ST/AUDUBON AV"
                  ]
                }
              },
              "RecordedAtTime": "2025-04-01T04:13:00.035-04:00"
            },
            {
              "MonitoredVehicleJourney": {
                "LineRef": "MTA NYCT_M7",
                "DirectionRef": "1",
                "FramedVehicleJourneyRef": {
                  "DataFrameRef": "2025-04-01",
                  "DatedVehicleJourneyRef": "MTA NYCT_OF_B5-Weekday-SDon-022000_M7_202"
                },
                "PublishedLineName": [
                  "M7"
                ],
                "DestinationRef": "MTA_903325",
                "DestinationName": [
                  "14 ST via COLUMBUS via 7 AV"
                ],
                "SituationRef": [
                  {
                    "SituationSimpleRef": "MTA NYCT_lmm:alert:420753"
                  }
                ],
                "Monitored": true,
                "VehicleLocation": {
                  "Longitude": -73.983713,
                  "Latitude": 40.760388
                },
                "Bearing": 233.90242,
                "ProgressRate": "normalProgress",
                "VehicleRef": "MTA NYCT_9566",
                "MonitoredCall": {
                  "AimedArrivalTime": "2025-04-01T04:10:23.469-04:00",
                  "ExpectedArrivalTime": "2025-04-01T04:13:49.972-04:00",
                  "ArrivalProximityText": "< 1 stop away",
                  "ExpectedDepartureTime": "2025-04-01T04:13:49.972-04:00",
                  "DistanceFromStop": 373,
                  "NumberOfStopsAway": 0,
                  "Extensions": {
                    "Capacities": {
                      "EstimatedPassengerCount": 1,
                      "EstimatedPassengerCapacity": 80
                    }
                  },
                  "VisitNumber": 1,
                  "StopPointName": [
                    "7 AV/W 44 ST"
                  ]
                }
              },
              "RecordedAtTime": "2025-04-01T04:13:02.000-04:00"
            },
            {
              "MonitoredVehicleJourney": {
                "LineRef": "MTA NYCT_M1",
                "DirectionRef": "1",
                "FramedVehicleJourneyRef": {
                  "DataFrameRef": "2025-04-01",
                  "DatedVehicleJourneyRef": "MTA NYCT_OF_B5-Weekday-SDon-024000_M1_101"
                },
                "PublishedLineName": [
                  "M1"
                ],
                "DestinationRef": "MTA_404823",
                "DestinationName": [
                  "SOHO CENTRE ST via 5 AV/ via BROADWAY"
                ],
                "SituationRef": [
                  {
                    "SituationSimpleRef": "MTA NYCT_lmm:alert:420753"
                  },
                  {
                    "SituationSimpleRef": "MTA NYCT_lmm:planned_work:22663"
                  },
                  {
                    "SituationSimpleRef": "MTA NYCT_lmm:planned_work:23502"
                  }
                ],
                "Monitored": true,
                "VehicleLocation": {
                  "Longitude": -73.949654,
                  "Latitude": 40.79628
                },
                "Bearing": 236.26514,
                "ProgressRate": "normalProgress",
                "VehicleRef": "MTA NYCT_9569",
                "MonitoredCall": {
                  "AimedArrivalTime": "2025-04-01T04:11:23.475-04:00",
                  "ExpectedArrivalTime": "2025-04-01T04:13:18.555-04:00",
                  "ArrivalProximityText": "approaching",
                  "ExpectedDepartureTime": "2025-04-01T04:13:18.555-04:00",
                  "DistanceFromStop": 101,
                  "NumberOfStopsAway": 0,
                  "Extensions": {
                    "Capacities": {
                      "EstimatedPassengerCount": 8,
                      "EstimatedPassengerCapacity": 80
                    }
                  },
                  "VisitNumber": 1,
                  "StopPointName": [
                    "5 AV/E 108 ST"
                  ]
                }
              },
              "RecordedAtTime": "2025-04-01T04:12:54.000-04:00"
            },
            {
              "MonitoredVehicleJourney": {
                "LineRef": "MTA NYCT_M7",
                "DirectionRef": "0",
                "FramedVehicleJourneyRef": {
                  "DataFrameRef": "2025-04-01",
                  "DatedVehicleJourneyRef": "MTA NYCT_OF_B5-Weekday-SDon-022000_M7_201"
                },
                "PublishedLineName": [
                  "M7"
                ],
                "DestinationRef": "MTA_400067",
                "DestinationName": [
                  "HARLEM 147 ST via 6 AV via AMSTERDAM"
                ],
                "SituationRef": [
                  {
                    "SituationSimpleRef": "MTA NYCT_lmm:alert:420753"
                  }
                ],
                "Monitored": true,
                "VehicleLocation": {
                  "Longitude": -73.943694,
                  "Latitude": 40.810111
                },
                "Bearing": 53.864624,
                "ProgressRate": "normalProgress",
                "VehicleRef": "MTA NYCT_9584",
                "MonitoredCall": {
                  "AimedArrivalTime": "2025-04-01T04:12:10.492-04:00",
                  "ExpectedArrivalTime": "2025-04-01T04:13:13.229-04:00",
                  "ArrivalProximityText": "approaching",
                  "ExpectedDepartureTime": "2025-04-01T04:13:13.229-04:00",
                  "DistanceFromStop": 70,
                  "NumberOfStopsAway": 0,
                  "Extensions": {
                    "Capacities": {
                      "EstimatedPassengerCount": 4,
                      "EstimatedPassengerCapacity": 80
                    }
                  },
                  "VisitNumber": 1,
                  "StopPointName": [
                    "MALCOLM X BLVD/W 129 ST"
                  ]
                }
              },
              "RecordedAtTime": "2025-04-01T04:12:57.522-04:00"
            },
            {
              "MonitoredVehicleJourney": {
                "LineRef": "MTA NYCT_M15",
                "DirectionRef": "0",
                "FramedVehicleJourneyRef": {
                  "DataFrameRef": "2025-04-01",
                  "DatedVehicleJourneyRef": "MTA NYCT_OH_B5-Weekday-SDon-024000_M15_203"
                },
                "PublishedLineName": [
                  "M15"
                ],
                "DestinationRef": "MTA_803054",
                "DestinationName": [
                  "EAST HARLEM 125 ST via 1 AV"
                ],
                "SituationRef": [
                  {
                    "SituationSimpleRef": "MTA NYCT_lmm:alert:420753"
                  },
                  {
                    "SituationSimpleRef": "MTA NYCT_lmm:planned_work:10129"
                  },
                  {
                    "SituationSimpleRef": "MTA NYCT_lmm:planned_work:21502"
                  }
                ],
                "Monitored": true,
                "VehicleLocation": {
                  "Longitude": -73.989929,
                  "Latitude": 40.719817
                },
                "Bearing": 63.252728,
                "ProgressRate": "normalProgress",
                "VehicleRef": "MTA NYCT_5969",
                "MonitoredCall": {
                  "AimedArrivalTime": "2025-04-01T04:13:15.573-04:00",
                  "ExpectedArrivalTime": "2025-04-01T04:14:00.059-04:00",
                  "ArrivalProximityText": "< 1 stop away",
                  "ExpectedDepartureTime": "2025-04-01T04:14:00.059-04:00",
                  "DistanceFromStop": 248,
                  "NumberOfStopsAway": 0,
                  "VisitNumber": 1,
                  "StopPointName": [
                    "ALLEN ST/STANTON ST"
                  ]
                }
              },
              "RecordedAtTime": "2025-04-01T04:13:04.000-04:00"
            },
            {
              "MonitoredVehicleJourney": {
                "LineRef": "MTA NYCT_M102",
                "DirectionRef": "0",
                "FramedVehicleJourneyRef": {
                  "DataFrameRef": "2025-04-01",
                  "DatedVehicleJourneyRef": "MTA NYCT_OH_B5-Weekday-SDon-025200_M101_5"
                },
                "PublishedLineName": [
                  "M102"
                ],
                "DestinationRef": "MTA_803024",
                "DestinationName": [
                  "HARLEM 147 ST via 3 AV via LENOX AV"
                ],
                "SituationRef": [
                  {
                    "SituationSimpleRef": "MTA NYCT_lmm:alert:420753"
                  },
                  {
                    "SituationSimpleRef": "MTA NYCT_lmm:planned_work:21837"
                  },
                  {
                    "SituationSimpleRef": "MTA NYCT_lmm:planned_work:23451"
                  }
                ],
                "Monitored": true,
                "VehicleLocation": {
                  "Longitude": -73.989964,
                  "Latitude": 40.729582
                },
                "Bearing": 340.05762,
                "ProgressRate": "normalProgress",
                "VehicleRef": "MTA NYCT_5957",
                "MonitoredCall": {
                  "AimedArrivalTime": "2025-04-01T04:12:22.587-04:00",
                  "ArrivalProximityText": "approaching",
                  "DistanceFromStop": 113,
                  "NumberOfStopsAway": 0,
                  "VisitNumber": 1,
                  "StopPointName": [
                    "3 AV/E 9 ST"
                  ]
                }
              },
              "RecordedAtTime": "2025-04-01T04:12:45.000-04:00"
            },
            {
              "MonitoredVehicleJourney": {
                "LineRef": "MTA NYCT_M102",
                "DirectionRef": "1",
                "FramedVehicleJourneyRef": {
                  "DataFrameRef": "2025-04-01",
                  "DatedVehicleJourneyRef": "MTA NYCT_OH_B5-Weekday-SDon-024600_M101_4"
                },
                "PublishedLineName": [
                  "M102"
                ],
                "DestinationRef": "MTA_404092",
                "DestinationName": [
                  "EAST VILLAGE 6 ST via LEX AV"
                ],
                "SituationRef": [
                  {
                    "SituationSimpleRef": "MTA NYCT_lmm:alert:420753"
                  },
                  {
                    "SituationSimpleRef": "MTA NYCT_lmm:planned_work:21837"
                  },
                  {
                    "SituationSimpleRef": "MTA NYCT_lmm:planned_work:23451"
                  }
                ],
                "Monitored": true,
                "VehicleLocation": {
                  "Longitude": -73.947249,
                  "Latitude": 40.805463
                },
                "Bearing": 233.71616,
                "ProgressRate": "normalProgress",
                "VehicleRef": "MTA NYCT_5927",
                "MonitoredCall": {
                  "AimedArrivalTime": "2025-04-01T04:15:54.743-04:00",
                  "ExpectedArrivalTime": "2025-04-01T04:13:18.538-04:00",
                  "ArrivalProximityText": "< 1 stop away",
                  "ExpectedDepartureTime": "2025-04-01T04:13:18.538-04:00",
                  "DistanceFromStop": 236,
                  "NumberOfStopsAway": 0,
                  "VisitNumber": 1,
                  "StopPointName": [
                    "MALCOLM X BLVD/W 119 ST"
                  ]
                }
              },
              "RecordedAtTime": "2025-04-01T04:12:47.000-04:00"
            },
            {
              "MonitoredVehicleJourney": {
                "LineRef": "MTA NYCT_M125",
                "DirectionRef": "1",
                "FramedVehicleJourneyRef": {
                  "DataFrameRef": "2025-04-01",
                  "DatedVehicleJourneyRef": "MTA NYCT_OF_B5-Weekday-SDon-024000_M125_502"
                },
                "PublishedLineName": [
                  "M125"
                ],
                "DestinationRef": "MTA_403829",
                "DestinationName": [
                  "MANHATTANVILLE 12 AV via 125 ST"
                ],
                "SituationRef": [
                  {
                    "SituationSimpleRef": "MTA NYCT_lmm:alert:420753"
                  }
                ],
                "Monitored": true,
                "VehicleLocation": {
                  "Longitude": -73.934199,
                  "Latitude": 40.803024
                },
                "Bearing": 157.45155,
                "ProgressRate": "normalProgress",
                "VehicleRef": "MTA NYCT_5292",
                "MonitoredCall": {
                  "AimedArrivalTime": "2025-04-01T04:12:00.771-04:00",
                  "ExpectedArrivalTime": "2025-04-01T04:13:48.563-04:00",
                  "ArrivalProximityText": "< 1 stop away",
                  "ExpectedDepartureTime": "2025-04-01T04:13:48.563-04:00",
                  "DistanceFromStop": 197,
                  "NumberOfStopsAway": 0,
                  "VisitNumber": 1,
                  "StopPointName": [
                    "E 125 ST/3 AV"
                  ]
                }
              },
              "RecordedAtTime": "2025-04-01T04:12:58.090-04:00"
            },
            {
              "MonitoredVehicleJourney": {
                "LineRef": "MTA NYCT_M10",
                "DirectionRef": "1",
                "FramedVehicleJourneyRef": {
                  "DataFrameRef": "2025-04-01",
                  "DatedVehicleJourneyRef": "MTA NYCT_MV_B5-Weekday-SDon-029000_M10_1"
                },
                "PublishedLineName": [
                  "M10"
                ],
                "DestinationRef": "MTA_405376",
                "DestinationName": [
                  "57 ST-BROADWAY via CENTRAL PK W."
                ],
                "SituationRef": [
                  {
                    "SituationSimpleRef": "MTA NYCT_lmm:alert:420753"
                  }
                ],
                "Monitored": true,
                "VehicleLocation": {
                  "Longitude": -73.936307,
                  "Latitude": 40.830428
                },
                "Bearing": 232.27501,
                "ProgressRate": "noProgress",
                "ProgressStatus": [
                  "layover"
                ],
                "VehicleRef": "MTA NYCT_9641",
                "MonitoredCall": {
                  "AimedArrivalTime": "2025-04-01T04:50:00.782-04:00",
                  "ArrivalProximityText": "at stop",
                  "DistanceFromStop": 0,
                  "NumberOfStopsAway": 0,
                  "VisitNumber": 1,
                  "StopPointName": [
                    "FREDERICK DOUGLASS BLVD/W 158 ST"
                  ]
                }
              },
              "RecordedAtTime": "2025-04-01T04:12:59.030-04:00"
            },
            {
              "MonitoredVehicleJourney": {
                "LineRef": "MTA NYCT_M100",
                "DirectionRef": "1",
                "FramedVehicleJourneyRef": {
                  "DataFrameRef": "2025-04-01",
                  "DatedVehicleJourneyRef": "MTA NYCT_KB_B5-Weekday-SDon-024000_M100_1"
                },
                "PublishedLineName": [
                  "M100"
                ],
                "DestinationRef": "MTA_903326",
                "DestinationName": [
                  "MANHTTNVILLE  W 125 via BWAY via AMSTRDM"
                ],
                "SituationRef": [
                  {
                    "SituationSimpleRef": "MTA NYCT_lmm:alert:420753"
                  }
                ],
                "Monitored": true,
                "VehicleLocation": {
                  "Longitude": -73.92794,
                  "Latitude": 40.865166
                },
                "Bearing": 207.91574,
                "ProgressRate": "normalProgress",
                "VehicleRef": "MTA NYCT_9664",
                "MonitoredCall": {
                  "AimedArrivalTime": "2025-04-01T04:13:00.802-04:00",
                  "ExpectedArrivalTime": "2025-04-01T04:13:12.129-04:00",
                  "ArrivalProximityText": "at stop",
                  "ExpectedDepartureTime": "2025-04-01T04:13:12.129-04:00",
                  "DistanceFromStop": 10,
                  "NumberOfStopsAway": 0,
                  "VisitNumber": 1,
                  "StopPointName": [
                    "BROADWAY/RIVERSIDE DR"
                  ]
                }
              },
              "RecordedAtTime": "2025-04-01T04:13:08.642-04:00"
            },
            {
              "MonitoredVehicleJourney": {
                "LineRef": "MTA NYCT_M125",
                "DirectionRef": "0",
                "FramedVehicleJourneyRef": {
                  "DataFrameRef": "2025-04-01",
                  "DatedVehicleJourneyRef": "MTA NYCT_OF_B5-Weekday-SDon-024000_M125_501"
                },
                "PublishedLineName": [
                  "M125"
                ],
                "DestinationRef": "MTA_103772",
                "DestinationName": [
                  "THE HUB 3 AV/149 ST via 125 ST"
                ],
                "SituationRef": [
                  {
                    "SituationSimpleRef": "MTA NYCT_lmm:alert:420753"
                  }
                ],
                "Monitored": true,
                "VehicleLocation": {
                  "Longitude": -73.941779,
                  "Latitude": 40.806224
                },
                "Bearing": 336.813,
                "ProgressRate": "normalProgress",
                "VehicleRef": "MTA NYCT_5264",
                "MonitoredCall": {
                  "AimedArrivalTime": "2025-04-01T04:09:00.879-04:00",
                  "ExpectedArrivalTime": "2025-04-01T04:13:22.742-04:00",
                  "ArrivalProximityText": "approaching",
                  "ExpectedDepartureTime": "2025-04-01T04:13:22.742-04:00",
                  "DistanceFromStop": 146,
                  "NumberOfStopsAway": 0,
                  "VisitNumber": 1,
                  "StopPointName": [
                    "E 125 ST/MADISON AV"
                  ]
                }
              },
              "RecordedAtTime": "2025-04-01T04:12:50.000-04:00"
            },
            {
              "MonitoredVehicleJourney": {
                "LineRef": "MTA NYCT_M79+",
                "DirectionRef": "0",
                "FramedVehicleJourneyRef": {
                  "DataFrameRef": "2025-04-01",
                  "DatedVehicleJourneyRef": "MTA NYCT_MQ_B5-Weekday-SDon-027000_SB79_652"
                },
                "PublishedLineName": [
                  "M79-SBS"
                ],
                "DestinationRef": "MTA_401878",
                "DestinationName": [
                  "SELECT BUS YRKVLLE EAST END AV CROSSTOWN"
                ],
                "OriginAimedDepartureTime": "2025-04-01T04:30:00.000-04:00",
                "SituationRef": [
                  {
                    "SituationSimpleRef": "MTA NYCT_lmm:planned_work:18087"
                  },
                  {
                    "SituationSimpleRef": "MTA NYCT_lmm:alert:420753"
                  }
                ],
                "Monitored": true,
                "VehicleLocation": {
                  "Longitude": -73.981931,
                  "Latitude": 40.784665
                },
                "Bearing": 337.55447,
                "ProgressRate": "noProgress",
                "ProgressStatus": [
                  "layover"
                ],
                "VehicleRef": "MTA NYCT_6228",
                "MonitoredCall": {
                  "AimedArrivalTime": "2025-04-01T04:32:00.102-04:00",
                  "ExpectedArrivalTime": "2025-04-01T04:13:31.104-04:00",
                  "ArrivalProximityText": "< 1 stop away",
                  "ExpectedDepartureTime": "2025-04-01T04:13:31.104-04:00",
                  "DistanceFromStop": 164,
                  "NumberOfStopsAway": 0,
                  "VisitNumber": 1,
                  "StopPointName": [
                    "W 79 ST/BROADWAY"
                  ]
                }
              },
              "RecordedAtTime": "2025-04-01T04:13:06.000-04:00"
            },
            {
              "MonitoredVehicleJourney": {
                "LineRef": "MTA NYCT_M101",
                "DirectionRef": "0",
                "FramedVehicleJourneyRef": {
                  "DataFrameRef": "2025-04-01",
                  "DatedVehicleJourneyRef": "MTA NYCT_OH_B5-Weekday-SDon-024800_M101_9"
                },
                "PublishedLineName": [
                  "M101"
                ],
                "DestinationRef": "MTA_903360",
                "DestinationName": [
                  "FT GEORGE via 3 AV via AMSTERDAM AV"
                ],
                "SituationRef": [
                  {
                    "SituationSimpleRef": "MTA NYCT_lmm:alert:420753"
                  },
                  {
                    "SituationSimpleRef": "MTA NYCT_lmm:planned_work:21837"
                  },
                  {
                    "SituationSimpleRef": "MTA NYCT_lmm:planned_work:23451"
                  }
                ],
                "Monitored": true,
                "VehicleLocation": {
                  "Longitude": -73.938857,
                  "Latitude": 40.799519
                },
                "Bearing": 53.86139,
                "ProgressRate": "normalProgress",
                "VehicleRef": "MTA NYCT_5778",
                "MonitoredCall": {
                  "AimedArrivalTime": "2025-04-01T04:13:21.145-04:00",
                  "ExpectedArrivalTime": "2025-04-01T04:13:10.869-04:00",
                  "ArrivalProximityText": "at stop",
                  "ExpectedDepartureTime": "2025-04-01T04:13:10.869-04:00",
                  "DistanceFromStop": 11,
                  "NumberOfStopsAway": 0,
                  "VisitNumber": 1,
                  "StopPointName": [
                    "3 AV/E 118 ST"
                  ]
                }
              },
              "RecordedAtTime": "2025-04-01T04:12:54.000-04:00"
            },
            {
              "MonitoredVehicleJourney": {
                "LineRef": "MTA NYCT_M116",
                "DirectionRef": "0",
                "FramedVehicleJourneyRef": {
                  "DataFrameRef": "2025-04-01",
                  "DatedVehicleJourneyRef": "MTA NYCT_MV_B5-Weekday-SDon-030000_M116_702"
                },
                "PublishedLineName": [
                  "M116"
                ],
                "DestinationRef": "MTA_803059",
                "DestinationName": [
                  "EAST HARLEM PALADINO AV CROSSTOWN"
                ],
                "OriginAimedDepartureTime": "2025-04-01T05:00:00.000-04:00",
                "SituationRef": [
                  {
                    "SituationSimpleRef": "MTA NYCT_lmm:alert:420753"
                  }
                ],
                "Monitored": true,
                "VehicleLocation": {
                  "Longitude": -73.967544,
                  "Latitude": 40.801198
                },
                "Bearing": 337.45294,
                "ProgressRate": "noProgress",
                "ProgressStatus": [
                  "layover"
                ],
                "VehicleRef": "MTA NYCT_9450",
                "MonitoredCall": {
                  "AimedArrivalTime": "2025-04-01T05:00:00.180-04:00",
                  "ArrivalProximityText": "at stop",
                  "DistanceFromStop": 0,
                  "NumberOfStopsAway": 0,
                  "VisitNumber": 1,
                  "StopPointName": [
                    "W 106 ST/BROADWAY"
                  ]
                }
              },
              "RecordedAtTime": "2025-04-01T04:12:47.127-04:00"
            },
            {
              "MonitoredVehicleJourney": {
                "LineRef": "MTA NYCT_M104",
                "DirectionRef": "0",
                "FramedVehicleJourneyRef": {
                  "DataFrameRef": "2025-04-01",
                  "DatedVehicleJourneyRef": "MTA NYCT_MV_B5-Weekday-SDon-024500_M104_102"
                },
                "PublishedLineName": [
                  "M104"
                ],
                "DestinationRef": "MTA_903352",
                "DestinationName": [
                  "WEST HARLEM 129 ST via BROADWAY"
                ],
                "SituationRef": [
                  {
                    "SituationSimpleRef": "MTA NYCT_lmm:alert:420753"
                  },
                  {
                    "SituationSimpleRef": "MTA NYCT_lmm:planned_work:15147"
                  }
                ],
                "Monitored": true,
                "VehicleLocation": {
                  "Longitude": -73.981605,
                  "Latitude": 40.779568
                },
                "Bearing": 72.49914,
                "ProgressRate": "normalProgress",
                "VehicleRef": "MTA NYCT_9455",
                "MonitoredCall": {
                  "AimedArrivalTime": "2025-04-01T04:13:47.186-04:00",
                  "ExpectedArrivalTime": "2025-04-01T04:13:10.869-04:00",
                  "ArrivalProximityText": "at stop",
                  "ExpectedDepartureTime": "2025-04-01T04:13:10.869-04:00",
                  "DistanceFromStop": 3,
                  "NumberOfStopsAway": 0,
                  "VisitNumber": 1,
                  "StopPointName": [
                    "BROADWAY/W 73 ST"
                  ]
                }
              },
              "RecordedAtTime": "2025-04-01T04:12:39.000-04:00"
            },
            {
              "MonitoredVehicleJourney": {
                "LineRef": "MTA NYCT_M104",
                "DirectionRef": "1",
                "FramedVehicleJourneyRef": {
                  "DataFrameRef": "2025-04-01",
                  "DatedVehicleJourneyRef": "MTA NYCT_MV_B5-Weekday-SDon-024500_M104_101"
                },
                "PublishedLineName": [
                  "M104"
                ],
                "DestinationRef": "MTA_404153",
                "DestinationName": [
                  "41 ST via BROADWAY/7 AV"
                ],
                "SituationRef": [
                  {
                    "SituationSimpleRef": "MTA NYCT_lmm:alert:420753"
                  },
                  {
                    "SituationSimpleRef": "MTA NYCT_lmm:planned_work:15147"
                  }
                ],
                "Monitored": true,
                "VehicleLocation": {
                  "Longitude": -73.964022,
                  "Latitude": 40.808005
                },
                "Bearing": 233.91972,
                "ProgressRate": "normalProgress",
                "VehicleRef": "MTA NYCT_9440",
                "MonitoredCall": {
                  "AimedArrivalTime": "2025-04-01T04:12:40.194-04:00",
                  "ExpectedArrivalTime": "2025-04-01T04:13:10.869-04:00",
                  "ArrivalProximityText": "at stop",
                  "ExpectedDepartureTime": "2025-04-01T04:13:10.869-04:00",
                  "DistanceFromStop": 12,
                  "NumberOfStopsAway": 0,
                  "Extensions": {
                    "Capacities": {
                      "EstimatedPassengerCount": 1,
                      "EstimatedPassengerCapacity": 80
                    }
                  },
                  "VisitNumber": 1,
                  "StopPointName": [
                    "BROADWAY/W 116 ST"
                  ]
                }
              },
              "RecordedAtTime": "2025-04-01T04:12:41.069-04:00"
            },
            {
              "MonitoredVehicleJourney": {
                "LineRef": "MTA NYCT_M15",
                "DirectionRef": "1",
                "FramedVehicleJourneyRef": {
                  "DataFrameRef": "2025-04-01",
                  "DatedVehicleJourneyRef": "MTA NYCT_OH_B5-Weekday-SDon-024500_M15_206"
                },
                "PublishedLineName": [
                  "M15"
                ],
                "DestinationRef": "MTA_803002",
                "DestinationName": [
                  "SOUTH FERRY via 2 AV"
                ],
                "SituationRef": [
                  {
                    "SituationSimpleRef": "MTA NYCT_lmm:alert:420753"
                  },
                  {
                    "SituationSimpleRef": "MTA NYCT_lmm:planned_work:10129"
                  },
                  {
                    "SituationSimpleRef": "MTA NYCT_lmm:planned_work:21502"
                  }
                ],
                "Monitored": true,
                "VehicleLocation": {
                  "Longitude": -73.94414,
                  "Latitude": 40.788283
                },
                "Bearing": 233.1301,
                "ProgressRate": "normalProgress",
                "VehicleRef": "MTA NYCT_5845",
                "MonitoredCall": {
                  "AimedArrivalTime": "2025-04-01T04:12:52.321-04:00",
                  "ExpectedArrivalTime": "2025-04-01T04:13:13.095-04:00",
                  "ArrivalProximityText": "approaching",
                  "ExpectedDepartureTime": "2025-04-01T04:13:13.095-04:00",
                  "DistanceFromStop": 121,
                  "NumberOfStopsAway": 0,
                  "VisitNumber": 1,
                  "StopPointName": [
                    "2 AV/E 101 ST"
                  ]
                }
              },
              "RecordedAtTime": "2025-04-01T04:12:56.000-04:00"
            },
            {
              "MonitoredVehicleJourney": {
                "LineRef": "MTA NYCT_M103",
                "DirectionRef": "1",
                "FramedVehicleJourneyRef": {
                  "DataFrameRef": "2025-04-01",
                  "DatedVehicleJourneyRef": "MTA NYCT_OH_B5-Weekday-SDon-023400_M101_8"
                },
                "PublishedLineName": [
                  "M103"
                ],
                "DestinationRef": "MTA_404142",
                "DestinationName": [
                  "CITY HALL via LEX AV"
                ],
                "SituationRef": [
                  {
                    "SituationSimpleRef": "MTA NYCT_lmm:alert:420753"
                  },
                  {
                    "SituationSimpleRef": "MTA NYCT_lmm:planned_work:21837"
                  },
                  {
                    "SituationSimpleRef": "MTA NYCT_lmm:planned_work:23451"
                  }
                ],
                "Monitored": true,
                "VehicleLocation": {
                  "Longitude": -73.96026,
                  "Latitude": 40.773083
                },
                "Bearing": 233.8366,
                "ProgressRate": "normalProgress",
                "VehicleRef": "MTA NYCT_5834",
                "MonitoredCall": {
                  "AimedArrivalTime": "2025-04-01T04:06:46.333-04:00",
                  "ExpectedArrivalTime": "2025-04-01T04:13:23.162-04:00",
                  "ArrivalProximityText": "< 1 stop away",
                  "ExpectedDepartureTime": "2025-04-01T04:13:23.162-04:00",
                  "DistanceFromStop": 216,
                  "NumberOfStopsAway": 0,
                  "VisitNumber": 1,
                  "StopPointName": [
                    "LEXINGTON AV/E 74 ST"
                  ]
                }
              },
              "RecordedAtTime": "2025-04-01T04:12:56.000-04:00"
            },
            {
              "MonitoredVehicleJourney": {
                "LineRef": "MTA NYCT_M101",
                "DirectionRef": "1",
                "FramedVehicleJourneyRef": {
                  "DataFrameRef": "2025-04-01",
                  "DatedVehicleJourneyRef": "MTA NYCT_OH_B5-Weekday-SDon-019000_M101_6"
                },
                "PublishedLineName": [
                  "M101"
                ],
                "DestinationRef": "MTA_404092",
                "DestinationName": [
                  "EAST VILLAGE 3 AV-6 ST via LEX AV"
                ],
                "SituationRef": [
                  {
                    "SituationSimpleRef": "MTA NYCT_lmm:alert:420753"
                  },
                  {
                    "SituationSimpleRef": "MTA NYCT_lmm:planned_work:21837"
                  },
                  {
                    "SituationSimpleRef": "MTA NYCT_lmm:planned_work:23451"
                  }
                ],
                "Monitored": true,
                "VehicleLocation": {
                  "Longitude": -73.988972,
                  "Latitude": 40.730816
                },
                "Bearing": 233.60722,
                "ProgressRate": "normalProgress",
                "VehicleRef": "MTA NYCT_5866",
                "MonitoredCall": {
                  "AimedArrivalTime": "2025-04-01T04:15:00.342-04:00",
                  "ExpectedArrivalTime": "2025-04-01T04:13:34.710-04:00",
                  "ArrivalProximityText": "< 1 stop away",
                  "ExpectedDepartureTime": "2025-04-01T04:13:34.710-04:00",
                  "DistanceFromStop": 195,
                  "NumberOfStopsAway": 0,
                  "VisitNumber": 1,
                  "StopPointName": [
                    "COOPER SQ/E 7 ST"
                  ]
                }
              },
              "RecordedAtTime": "2025-04-01T04:12:46.000-04:00"
            },
            {
              "MonitoredVehicleJourney": {
                "LineRef": "MTA NYCT_M15",
                "DirectionRef": "0",
                "FramedVehicleJourneyRef": {
                  "DataFrameRef": "2025-04-01",
                  "DatedVehicleJourneyRef": "MTA NYCT_OH_B5-Weekday-SDon-018000_M15_201"
                },
                "PublishedLineName": [
                  "M15"
                ],
                "DestinationRef": "MTA_803054",
                "DestinationName": [
                  "EAST HARLEM 125 ST via 1 AV"
                ],
                "OriginAimedDepartureTime": "2025-04-01T04:32:00.000-04:00",
                "SituationRef": [
                  {
                    "SituationSimpleRef": "MTA NYCT_lmm:alert:420753"
                  },
                  {
                    "SituationSimpleRef": "MTA NYCT_lmm:planned_work:10129"
                  },
                  {
                    "SituationSimpleRef": "MTA NYCT_lmm:planned_work:21502"
                  }
                ],
                "Monitored": true,
                "VehicleLocation": {
                  "Longitude": -73.932034,
                  "Latitude": 40.80299
                },
                "Bearing": 157.09422,
                "ProgressRate": "noProgress",
                "ProgressStatus": [
                  "layover"
                ],
                "VehicleRef": "MTA NYCT_5827",
                "MonitoredCall": {
                  "AimedArrivalTime": "2025-04-01T03:43:00.446-04:00",
                  "ExpectedArrivalTime": "2025-04-01T04:13:10.869-04:00",
                  "ArrivalProximityText": "at stop",
                  "ExpectedDepartureTime": "2025-04-01T04:13:10.869-04:00",
                  "DistanceFromStop": 25,
                  "NumberOfStopsAway": 0,
                  "VisitNumber": 1,
                  "StopPointName": [
                    "E 126 ST/2 AV"
                  ]
                }
              },
              "RecordedAtTime": "2025-04-01T04:12:51.000-04:00"
            },
            {
              "MonitoredVehicleJourney": {
                "LineRef": "MTA NYCT_M14A+",
                "DirectionRef": "0",
                "FramedVehicleJourneyRef": {
                  "DataFrameRef": "2025-04-01",
                  "DatedVehicleJourneyRef": "MTA NYCT_MQ_B5-Weekday-SDon-024000_SBS14_702"
                },
                "PublishedLineName": [
                  "M14A-SBS"
                ],
                "DestinationRef": "MTA_903025",
                "DestinationName": [
                  "SELECT BUS LES GRAND-FDR via 14 ST"
                ],
                "SituationRef": [
                  {
                    "SituationSimpleRef": "MTA NYCT_lmm:alert:420753"
                  }
                ],
                "Monitored": true,
                "VehicleLocation": {
                  "Longitude": -73.982627,
                  "Latitude": 40.731362
                },
                "Bearing": 337.0483,
                "ProgressRate": "normalProgress",
                "VehicleRef": "MTA NYCT_5599",
                "MonitoredCall": {
                  "AimedArrivalTime": "2025-04-01T04:08:14.544-04:00",
                  "ExpectedArrivalTime": "2025-04-01T04:13:10.869-04:00",
                  "ArrivalProximityText": "approaching",
                  "ExpectedDepartureTime": "2025-04-01T04:13:10.869-04:00",
                  "DistanceFromStop": 48,
                  "NumberOfStopsAway": 0,
                  "VisitNumber": 1,
                  "StopPointName": [
                    "E 14 ST/1 AV"
                  ]
                }
              },
              "RecordedAtTime": "2025-04-01T04:12:50.000-04:00"
            },
            {
              "MonitoredVehicleJourney": {
                "LineRef": "MTA NYCT_M79+",
                "DirectionRef": "0",
                "FramedVehicleJourneyRef": {
                  "DataFrameRef": "2025-04-01",
                  "DatedVehicleJourneyRef": "MTA NYCT_MQ_B5-Weekday-SDon-024000_SB79_651"
                },
                "PublishedLineName": [
                  "M79-SBS"
                ],
                "DestinationRef": "MTA_401878",
                "DestinationName": [
                  "SELECT BUS YRKVLLE EAST END AV CROSSTOWN"
                ],
                "SituationRef": [
                  {
                    "SituationSimpleRef": "MTA NYCT_lmm:planned_work:18087"
                  },
                  {
                    "SituationSimpleRef": "MTA NYCT_lmm:alert:420753"
                  }
                ],
                "Monitored": true,
                "VehicleLocation": {
                  "Longitude": -73.958608,
                  "Latitude": 40.774832
                },
                "Bearing": 337.5312,
                "ProgressRate": "normalProgress",
                "VehicleRef": "MTA NYCT_5598",
                "MonitoredCall": {
                  "AimedArrivalTime": "2025-04-01T04:11:34.547-04:00",
                  "ExpectedArrivalTime": "2025-04-01T04:13:14.277-04:00",
                  "ArrivalProximityText": "approaching",
                  "ExpectedDepartureTime": "2025-04-01T04:13:14.277-04:00",
                  "DistanceFromStop": 109,
                  "NumberOfStopsAway": 0,
                  "Extensions": {
                    "Capacities": {
                      "EstimatedPassengerCount": 1,
                      "EstimatedPassengerCapacity": 100
                    }
                  },
                  "VisitNumber": 1,
                  "StopPointName": [
                    "E 79 ST/3 AV"
                  ]
                }
              },
              "RecordedAtTime": "2025-04-01T04:12:42.000-04:00"
            },
            {
              "MonitoredVehicleJourney": {
                "LineRef": "MTA NYCT_M86+",
                "DirectionRef": "0",
                "FramedVehicleJourneyRef": {
                  "DataFrameRef": "2025-04-01",
                  "DatedVehicleJourneyRef": "MTA NYCT_MQ_B5-Weekday-SDon-027200_SBS86_953"
                },
                "PublishedLineName": [
                  "M86-SBS"
                ],
                "DestinationRef": "MTA_403383",
                "DestinationName": [
                  "SELECT BUS YORKVILLE 1AV-92 ST CROSSTOWN"
                ],
                "OriginAimedDepartureTime": "2025-04-01T04:32:00.000-04:00",
                "SituationRef": [
                  {
                    "SituationSimpleRef": "MTA NYCT_lmm:alert:420753"
                  }
                ],
                "Monitored": true,
                "VehicleLocation": {
                  "Longitude": -73.977339,
                  "Latitude": 40.788657
                },
                "Bearing": 337.47443,
                "ProgressRate": "noProgress",
                "ProgressStatus": [
                  "layover"
                ],
                "VehicleRef": "MTA NYCT_5586",
                "MonitoredCall": {
                  "AimedArrivalTime": "2025-04-01T04:32:21.555-04:00",
                  "ArrivalProximityText": "approaching",
                  "DistanceFromStop": 56,
                  "NumberOfStopsAway": 0,
                  "VisitNumber": 1,
                  "StopPointName": [
                    "W 86 ST/BROADWAY"
                  ]
                }
              },
              "RecordedAtTime": "2025-04-01T04:12:42.000-04:00"
            },
            {
              "MonitoredVehicleJourney": {
                "LineRef": "MTA NYCT_M86+",
                "DirectionRef": "0",
                "FramedVehicleJourneyRef": {
                  "DataFrameRef": "2025-04-01",
                  "DatedVehicleJourneyRef": "MTA NYCT_MQ_B5-Weekday-SDon-026000_SBS86_951"
                },
                "PublishedLineName": [
                  "M86-SBS"
                ],
                "DestinationRef": "MTA_403383",
                "DestinationName": [
                  "SELECT BUS YORKVILLE 1AV-92 ST CROSSTOWN"
                ],
                "SituationRef": [
                  {
                    "SituationSimpleRef": "MTA NYCT_lmm:alert:420753"
                  }
                ],
                "Monitored": true,
                "VehicleLocation": {
                  "Longitude": -73.975921,
                  "Latitude": 40.788058
                },
                "Bearing": 337.56702,
                "ProgressRate": "normalProgress",
                "VehicleRef": "MTA NYCT_5513",
                "MonitoredCall": {
                  "AimedArrivalTime": "2025-04-01T04:20:53.609-04:00",
                  "ExpectedArrivalTime": "2025-04-01T04:13:10.869-04:00",
                  "ArrivalProximityText": "approaching",
                  "ExpectedDepartureTime": "2025-04-01T04:13:10.869-04:00",
                  "DistanceFromStop": 54,
                  "NumberOfStopsAway": 0,
                  "VisitNumber": 1,
                  "StopPointName": [
                    "W 86 ST/AMSTERDAM AV"
                  ]
                }
              },
              "RecordedAtTime": "2025-04-01T04:12:56.000-04:00"
            },
            {
              "MonitoredVehicleJourney": {
                "LineRef": "MTA NYCT_M23+",
                "DirectionRef": "0",
                "FramedVehicleJourneyRef": {
                  "DataFrameRef": "2025-04-01",
                  "DatedVehicleJourneyRef": "MTA NYCT_MQ_B5-Weekday-SDon-023900_SBS23_801"
                },
                "PublishedLineName": [
                  "M23-SBS"
                ],
                "DestinationRef": "MTA_903002",
                "DestinationName": [
                  "SELECT BUS EAST SIDE AVENUE C CROSSTOWN"
                ],
                "SituationRef": [
                  {
                    "SituationSimpleRef": "MTA NYCT_lmm:alert:420753"
                  }
                ],
                "Monitored": true,
                "VehicleLocation": {
                  "Longitude": -73.981161,
                  "Latitude": 40.737999
                },
                "Bearing": 337.85876,
                "ProgressRate": "normalProgress",
                "VehicleRef": "MTA NYCT_5518",
                "MonitoredCall": {
                  "AimedArrivalTime": "2025-04-01T04:10:37.613-04:00",
                  "ExpectedArrivalTime": "2025-04-01T04:13:10.869-04:00",
                  "ArrivalProximityText": "approaching",
                  "ExpectedDepartureTime": "2025-04-01T04:13:10.869-04:00",
                  "DistanceFromStop": 62,
                  "NumberOfStopsAway": 0,
                  "VisitNumber": 1,
                  "StopPointName": [
                    "E 23 ST/2 AV"
                  ]
                }
              },
              "RecordedAtTime": "2025-04-01T04:12:45.000-04:00"
            },
            {
              "MonitoredVehicleJourney": {
                "LineRef": "MTA NYCT_M2",
                "DirectionRef": "1",
                "FramedVehicleJourneyRef": {
                  "DataFrameRef": "2025-04-01",
                  "DatedVehicleJourneyRef": "MTA NYCT_MV_B5-Weekday-SDon-025000_M2_203"
                },
                "PublishedLineName": [
                  "M2"
                ],
                "DestinationRef": "MTA_404010",
                "DestinationName": [
                  "EAST VILLAGE 8 ST via 5 AV"
                ],
                "SituationRef": [
                  {
                    "SituationSimpleRef": "MTA NYCT_lmm:alert:420753"
                  },
                  {
                    "SituationSimpleRef": "MTA NYCT_lmm:planned_work:22663"
                  },
                  {
                    "SituationSimpleRef": "MTA NYCT_lmm:planned_work:23502"
                  }
                ],
                "Monitored": true,
                "VehicleLocation": {
                  "Longitude": -73.939894,
                  "Latitude": 40.838946
                },
                "Bearing": 272.7927,
                "ProgressRate": "normalProgress",
                "VehicleRef": "MTA NYCT_9910",
                "MonitoredCall": {
                  "AimedArrivalTime": "2025-04-01T04:11:55.620-04:00",
                  "ExpectedArrivalTime": "2025-04-01T04:13:36.561-04:00",
                  "ArrivalProximityText": "< 1 stop away",
                  "ExpectedDepartureTime": "2025-04-01T04:13:36.561-04:00",
                  "DistanceFromStop": 227,
                  "NumberOfStopsAway": 0,
                  "VisitNumber": 1,
                  "StopPointName": [
                    "W 165 ST/AMSTERDAM AV"
                  ]
                }
              },
              "RecordedAtTime": "2025-04-01T04:12:45.493-04:00"
            },
            {
              "MonitoredVehicleJourney": {
                "LineRef": "MTA NYCT_M14D+",
                "DirectionRef": "1",
                "FramedVehicleJourneyRef": {
                  "DataFrameRef": "2025-04-01",
                  "DatedVehicleJourneyRef": "MTA NYCT_MQ_B5-Weekday-SDon-024100_SBS14_701"
                },
                "PublishedLineName": [
                  "M14D-SBS"
                ],
                "DestinationRef": "MTA_903358",
                "DestinationName": [
                  "SELECT BUS CHLSEA PIERS  11 AV via 14 ST"
                ],
                "SituationRef": [
                  {
                    "SituationSimpleRef": "MTA NYCT_lmm:planned_work:9387"
                  },
                  {
                    "SituationSimpleRef": "MTA NYCT_lmm:alert:420753"
                  },
                  {
                    "SituationSimpleRef": "MTA NYCT_lmm:planned_work:22448"
                  }
                ],
                "Monitored": true,
                "VehicleLocation": {
                  "Longitude": -73.978323,
                  "Latitude": 40.729544
                },
                "Bearing": 157.47545,
                "ProgressRate": "normalProgress",
                "VehicleRef": "MTA NYCT_6188",
                "MonitoredCall": {
                  "AimedArrivalTime": "2025-04-01T04:10:45.659-04:00",
                  "ExpectedArrivalTime": "2025-04-01T04:13:36.164-04:00",
                  "ArrivalProximityText": "< 1 stop away",
                  "ExpectedDepartureTime": "2025-04-01T04:13:36.164-04:00",
                  "DistanceFromStop": 203,
                  "NumberOfStopsAway": 0,
                  "Extensions": {
                    "Capacities": {
                      "EstimatedPassengerCount": 11,
                      "EstimatedPassengerCapacity": 80
                    }
                  },
                  "VisitNumber": 1,
                  "StopPointName": [
                    "E 14 ST/AVENUE A"
                  ]
                }
              },
              "RecordedAtTime": "2025-04-01T04:12:49.000-04:00"
            },
            {
              "MonitoredVehicleJourney": {
                "LineRef": "MTA NYCT_M15",
                "DirectionRef": "1",
                "FramedVehicleJourneyRef": {
                  "DataFrameRef": "2025-04-01",
                  "DatedVehicleJourneyRef": "MTA NYCT_OH_B5-Weekday-SDon-023000_M15_205"
                },
                "PublishedLineName": [
                  "M15"
                ],
                "DestinationRef": "MTA_803002",
                "DestinationName": [
                  "SOUTH FERRY via 2 AV"
                ],
                "SituationRef": [
                  {
                    "SituationSimpleRef": "MTA NYCT_lmm:alert:420753"
                  },
                  {
                    "SituationSimpleRef": "MTA NYCT_lmm:planned_work:10129"
                  },
                  {
                    "SituationSimpleRef": "MTA NYCT_lmm:planned_work:21502"
                  }
                ],
                "Monitored": true,
                "VehicleLocation": {
                  "Longitude": -73.970791,
                  "Latitude": 40.751777
                },
                "Bearing": 234.02762,
                "ProgressRate": "normalProgress",
                "VehicleRef": "MTA NYCT_6101",
                "MonitoredCall": {
                  "AimedArrivalTime": "2025-04-01T04:13:00.727-04:00",
                  "ExpectedArrivalTime": "2025-04-01T04:14:00.484-04:00",
                  "ArrivalProximityText": "< 1 stop away",
                  "ExpectedDepartureTime": "2025-04-01T04:14:00.484-04:00",
                  "DistanceFromStop": 325,
                  "NumberOfStopsAway": 0,
                  "Extensions": {
                    "Capacities": {
                      "EstimatedPassengerCount": 6,
                      "EstimatedPassengerCapacity": 80
                    }
                  },
                  "VisitNumber": 1,
                  "StopPointName": [
                    "2 AV/E 41 ST"
                  ]
                }
              },
              "RecordedAtTime": "2025-04-01T04:13:09.000-04:00"
            },
            {
              "MonitoredVehicleJourney": {
                "LineRef": "MTA NYCT_M86+",
                "DirectionRef": "0",
                "FramedVehicleJourneyRef": {
                  "DataFrameRef": "2025-04-01",
                  "DatedVehicleJourneyRef": "MTA NYCT_MQ_B5-Weekday-SDon-024000_SBS86_952"
                },
                "PublishedLineName": [
                  "M86-SBS"
                ],
                "DestinationRef": "MTA_403383",
                "DestinationName": [
                  "SELECT BUS YORKVILLE 1AV-92 ST CROSSTOWN"
                ],
                "SituationRef": [
                  {
                    "SituationSimpleRef": "MTA NYCT_lmm:alert:420753"
                  }
                ],
                "Monitored": true,
                "VehicleLocation": {
                  "Longitude": -73.959398,
                  "Latitude": 40.78004
                },
                "Bearing": 53.864624,
                "ProgressRate": "normalProgress",
                "VehicleRef": "MTA NYCT_5600",
                "MonitoredCall": {
                  "AimedArrivalTime": "2025-04-01T04:08:07.800-04:00",
                  "ExpectedArrivalTime": "2025-04-01T04:13:22.570-04:00",
                  "ArrivalProximityText": "approaching",
                  "ExpectedDepartureTime": "2025-04-01T04:13:22.570-04:00",
                  "DistanceFromStop": 139,
                  "NumberOfStopsAway": 0,
                  "Extensions": {
                    "Capacities": {
                      "EstimatedPassengerCount": 1,
                      "EstimatedPassengerCapacity": 100
                    }
                  },
                  "VisitNumber": 1,
                  "StopPointName": [
                    "E 86 ST/MADISON AV"
                  ]
                }
              },
              "RecordedAtTime": "2025-04-01T04:12:41.000-04:00"
            }
          ]
        }
      ]
    }
  }
}