{
  "Siri": {
    "ServiceDelivery": {
      "VehicleMonitoringDelivery": [
        {
          "VehicleActivity": [
            {
              "MonitoredVehicleJourney": {
                "LineRef": "MTA NYCT_M42",
                "DirectionRef": "0",
                "FramedVehicleJourneyRef": {
                  "DataFrameRef": "2025-04-01",
                  "DatedVehicleJourneyRef": "MTA NYCT_MQ_B5-Weekday-SDon-019800_M42_301"
                },
                "PublishedLineName": [
                  "M42"
                ],
                "DestinationRef": "MTA_903046",
                "DestinationName": [
                  "EAST SIDE U N-1 AV CROSSTOWN"
                ],
                "SituationRef": [
                  {
                    "SituationSimpleRef": "MTA NYCT_lmm:alert:420753"
                  }
                ],
                "Monitored": true,
                "VehicleLocation": {
                  "Longitude": -73.994585,
                  "Latitude": 40.759247
                },
                "Bearing": 337.25763,
                "ProgressRate": "normalProgress",
                "VehicleRef": "MTA NYCT_9717",
                "MonitoredCall": {
                  "AimedArrivalTime": "2025-04-01T03:22:11.203-04:00",
                  "ExpectedArrivalTime": "2025-04-01T03:21:59.674-04:00",
                  "ArrivalProximityText": "< 1 stop away",
                  "ExpectedDepartureTime": "2025-04-01T03:21:59.674-04:00",
                  "DistanceFromStop": 265,
                  "NumberOfStopsAway": 0,
                  "Extensions": {
                    "Capacities": {
                      "EstimatedPassengerCount": 6,
                      "EstimatedPassengerCapacity": 80
                    }
                  },
                  "VisitNumber": 1,
                  "StopPointName": [
                    "W 42 ST/9 AV"
                  ]
                }
              },
              "RecordedAtTime": "2025-04-01T03:21:02.080-04:00"
            },
            {
              "MonitoredVehicleJourney": {
                "LineRef": "MTA NYCT_M15",
                "DirectionRef": "0",
                "FramedVehicleJourneyRef": {
                  "DataFrameRef": "2025-04-01",
                  "DatedVehicleJourneyRef": "MTA NYCT_OH_B5-Weekday-SDon-015000_M15_204"
                },
                "PublishedLineName": [
                  "M15"
                ],
                "DestinationRef": "MTA_803054",
                "DestinationName": [
                  "EAST HARLEM 125 ST via 1 AV"
                ],
                "OriginAimedDepartureTime": "2025-04-01T03:30:00.000-04:00",
                "SituationRef": [
                  {
                    "SituationSimpleRef": "MTA NYCT_lmm:planned_work:10129"
                  },
                  {
                    "SituationSimpleRef": "MTA NYCT_lmm:planned_work:21502"
                  },
                  {
                    "SituationSimpleRef": "MTA NYCT_lmm:alert:420753"
                  }
                ],
                "Monitored": true,
                "VehicleLocation": {
                  "Longitude": -73.932167,
                  "Latitude": 40.803046
                },
                "Bearing": 157.09422,
                "ProgressRate": "noProgress",
                "ProgressStatus": [
                  "layover"
                ],
                "VehicleRef": "MTA NYCT_5359",
                "MonitoredCall": {
                  "AimedArrivalTime": "2025-04-01T03:13:00.207-04:00",
                  "ExpectedArrivalTime": "2025-04-01T03:21:31.119-04:00",
                  "ArrivalProximityText": "at stop",
                  "ExpectedDepartureTime": "2025-04-01T03:21:31.119-04:00",
                  "DistanceFromStop": 12,
                  "NumberOfStopsAway": 0,
                  "VisitNumber": 1,
                  "StopPointName": [
                    "E 126 ST/2 AV"
                  ]
                }
              },
              "RecordedAtTime": "2025-04-01T03:21:27.000-04:00"
            },
            {
              "MonitoredVehicleJourney": {
                "LineRef": "MTA NYCT_M103",
                "DirectionRef": "1",
                "FramedVehicleJourneyRef": {
                  "DataFrameRef": "2025-04-01",
                  "DatedVehicleJourneyRef": "MTA NYCT_OH_B5-Weekday-SDon-017200_M101_7"
                },
                "PublishedLineName": [
                  "M103"
                ],
                "DestinationRef": "MTA_404142",
                "DestinationName": [
                  "CITY HALL via LEX AV"
                ],
                "SituationRef": [
                  {
                    "SituationSimpleRef": "MTA NYCT_lmm:planned_work:23451"
                  },
                  {
                    "SituationSimpleRef": "MTA NYCT_lmm:planned_work:21837"
                  },
                  {
                    "SituationSimpleRef": "MTA NYCT_lmm:alert:420753"
                  }
                ],
                "Monitored": true,
                "VehicleLocation": {
                  "Longitude": -73.987656,
                  "Latitude": 40.732637
                },
                "Bearing": 233.54033,
                "ProgressRate": "normalProgress",
                "VehicleRef": "MTA NYCT_5313",
                "MonitoredCall": {
                  "AimedArrivalTime": "2025-04-01T03:24:08.264-04:00",
                  "ExpectedArrivalTime": "2025-04-01T03:22:16.813-04:00",
                  "ArrivalProximityText": "< 1 stop away",
                  "ExpectedDepartureTime": "2025-04-01T03:22:16.813-04:00",
                  "DistanceFromStop": 214,
                  "NumberOfStopsAway": 0,
                  "VisitNumber": 1,
                  "StopPointName": [
                    "3 AV/E 11 ST"
                  ]
                }
              },
              "RecordedAtTime": "2025-04-01T03:21:24.000-04:00"
            },
            {
              "MonitoredVehicleJourney": {
                "LineRef": "MTA NYCT_M101",
                "DirectionRef": "0",
                "FramedVehicleJourneyRef": {
                  "DataFrameRef": "2025-04-01",
                  "DatedVehicleJourneyRef": "MTA NYCT_OH_B5-Weekday-SDon-015300_M101_2"
                },
                "PublishedLineName": [
                  "M101"
                ],
                "DestinationRef": "MTA_903360",
                "DestinationName": [
                  "FT GEORGE via 3 AV via AMSTERDAM AV"
                ],
                "SituationRef": [
                  {
                    "SituationSimpleRef": "MTA NYCT_lmm:planned_work:23451"
                  },
                  {
                    "SituationSimpleRef": "MTA NYCT_lmm:planned_work:21837"
                  },
                  {
                    "SituationSimpleRef": "MTA NYCT_lmm:alert:420753"
                  }
                ],
                "Monitored": true,
                "VehicleLocation": {
                  "Longitude": -73.943508,
                  "Latitude": 40.830838
                },
                "Bearing": 53.84452,
                "ProgressRate": "normalProgress",
                "VehicleRef": "MTA NYCT_5302",
                "MonitoredCall": {
                  "AimedArrivalTime": "2025-04-01T03:17:01.278-04:00",
                  "ExpectedArrivalTime": "2025-04-01T03:22:02.506-04:00",
                  "ArrivalProximityText": "approaching",
                  "ExpectedDepartureTime": "2025-04-01T03:22:02.506-04:00",
                  "DistanceFromStop": 109,
                  "NumberOfStopsAway": 0,
                  "VisitNumber": 1,
                  "StopPointName": [
                    "AMSTERDAM AV/W 155 ST"
                  ]
                }
              },
              "RecordedAtTime": "2025-04-01T03:21:18.000-04:00"
            },
            {
              "MonitoredVehicleJourney": {
                "LineRef": "MTA NYCT_M60+",
                "DirectionRef": "0",
                "FramedVehicleJourneyRef": {
                  "DataFrameRef": "2025-04-01",
                  "DatedVehicleJourneyRef": "MTA NYCT_MQ_B5-Weekday-SDon-019000_SBS60_901"
                },
                "PublishedLineName": [
                  "M60-SBS"
                ],
                "DestinationRef": "MTA_804142",
                "DestinationName": [
                  "SELECT BUS LA GUARDIA AIRPORT"
                ],
                "SituationRef": [
                  {
                    "SituationSimpleRef": "MTA NYCT_lmm:alert:420753"
                  }
                ],
                "Monitored": true,
                "VehicleLocation": {
                  "Longitude": -73.945687,
                  "Latitude": 40.807849
                },
                "Bearing": 337.44275,
                "ProgressRate": "normalProgress",
                "VehicleRef": "MTA NYCT_5454",
                "MonitoredCall": {
                  "AimedArrivalTime": "2025-04-01T03:21:57.364-04:00",
                  "ExpectedArrivalTime": "2025-04-01T03:21:31.119-04:00",
                  "ArrivalProximityText": "approaching",
                  "ExpectedDepartureTime": "2025-04-01T03:21:31.119-04:00",
                  "DistanceFromStop": 63,
                  "NumberOfStopsAway": 0,
                  "VisitNumber": 1,
                  "StopPointName": [
                    "W 125 ST/MALCOLM X  BLVD"
                  ]
                }
              },
              "RecordedAtTime": "2025-04-01T03:21:11.000-04:00"
            },
            {
              "MonitoredVehicleJourney": {
                "LineRef": "MTA NYCT_M60+",
                "DirectionRef": "0",
                "FramedVehicleJourneyRef": {
                  "DataFrameRef": "2025-04-01",
                  "DatedVehicleJourneyRef": "MTA NYCT_MQ_B5-Weekday-SDon-017000_SBS60_904"
                },
                "PublishedLineName": [
                  "M60-SBS"
                ],
                "DestinationRef": "MTA_804142",
                "DestinationName": [
                  "SELECT BUS LA GUARDIA AIRPORT"
                ],
                "SituationRef": [
                  {
                    "SituationSimpleRef": "MTA NYCT_lmm:alert:420753"
                  }
                ],
                "Monitored": true,
                "VehicleLocation": {
                  "Longitude": -73.899339,
                  "Latitude": 40.766964
                },
                "Bearing": 350.9868,
                "ProgressRate": "normalProgress",
                "VehicleRef": "MTA NYCT_5445",
                "MonitoredCall": {
                  "AimedArrivalTime": "2025-04-01T03:20:20.373-04:00",
                  "ExpectedArrivalTime": "2025-04-01T03:21:31.119-04:00",
                  "ArrivalProximityText": "< 1 stop away",
                  "ExpectedDepartureTime": "2025-04-01T03:21:31.119-04:00",
                  "DistanceFromStop": 683,
                  "NumberOfStopsAway": 0,
                  "VisitNumber": 1,
                  "StopPointName": [
                    "ASTORIA BLVD SOUTH/77 ST"
                  ]
                }
              },
              "RecordedAtTime": "2025-04-01T03:19:45.258-04:00"
            },
            {
              "MonitoredVehicleJourney": {
                "LineRef": "MTA NYCT_M60+",
                "DirectionRef": "0",
                "FramedVehicleJourneyRef": {
                  "DataFrameRef": "2025-04-01",
                  "DatedVehicleJourneyRef": "MTA NYCT_MQ_B5-Weekday-SDon-022500_SBS60_905"
                },
                "PublishedLineName": [
                  "M60-SBS"
                ],
                "DestinationRef": "MTA_804142",
                "DestinationName": [
                  "SELECT BUS LA GUARDIA AIRPORT"
                ],
                "OriginAimedDepartureTime": "2025-04-01T03:45:00.000-04:00",
                "SituationRef": [
                  {
                    "SituationSimpleRef": "MTA NYCT_lmm:alert:420753"
                  }
                ],
                "Monitored": true,
                "VehicleLocation": {
                  "Longitude": -73.967716,
                  "Latitude": 40.801821
                },
                "Bearing": 85.336655,
                "ProgressRate": "noProgress",
                "ProgressStatus": [
                  "layover"
                ],
                "VehicleRef": "MTA NYCT_5462",
                "MonitoredCall": {
                  "AimedArrivalTime": "2025-04-01T03:45:00.381-04:00",
                  "ArrivalProximityText": "at stop",
                  "DistanceFromStop": 0,
                  "NumberOfStopsAway": 0,
                  "VisitNumber": 1,
                  "StopPointName": [
                    "BROADWAY/W 106 ST"
                  ]
                }
              },
              "RecordedAtTime": "2025-04-01T03:21:13.000-04:00"
            },
            {
              "MonitoredVehicleJourney": {
                "LineRef": "MTA NYCT_M60+",
                "DirectionRef": "1",
                "FramedVehicleJourneyRef": {
                  "DataFrameRef": "2025-04-01",
                  "DatedVehicleJourneyRef": "MTA NYCT_MQ_B5-Weekday-SDon-018800_SBS60_903"
                },
                "PublishedLineName": [
                  "M60-SBS"
                ],
                "DestinationRef": "MTA_402018",
                "DestinationName": [
                  "SELECT BUS WEST SIDE BROADWAY-106 ST"
                ],
                "SituationRef": [
                  {
                    "SituationSimpleRef": "MTA NYCT_lmm:alert:420753"
                  }
                ],
                "Monitored": true,
                "VehicleLocation": {
                  "Longitude": -73.878205,
                  "Latitude": 40.771551
                },
                "Bearing": 215.53767,
                "ProgressRate": "normalProgress",
                "VehicleRef": "MTA NYCT_5467",
                "MonitoredCall": {
                  "AimedArrivalTime": "2025-04-01T03:15:31.385-04:00",
                  "ExpectedArrivalTime": "2025-04-01T03:24:50.156-04:00",
                  "ArrivalProximityText": "1.0 miles away",
                  "ExpectedDepartureTime": "2025-04-01T03:24:50.156-04:00",
                  "DistanceFromStop": 1625,
                  "NumberOfStopsAway": 0,
                  "VisitNumber": 1,
                  "StopPointName": [
                    "LGA/TERMINAL A - MARINE AIR TERMINAL"
                  ]
                }
              },
              "RecordedAtTime": "2025-04-01T03:21:01.000-04:00"
            },
            {
              "MonitoredVehicleJourney": {
                "LineRef": "MTA NYCT_M60+",
                "DirectionRef": "1",
                "FramedVehicleJourneyRef": {
                  "DataFrameRef": "2025-04-01",
                  "DatedVehicleJourneyRef": "MTA NYCT_MQ_B5-Weekday-SDon-016000_SBS60_902"
                },
                "PublishedLineName": [
                  "M60-SBS"
                ],
                "DestinationRef": "MTA_402018",
                "DestinationName": [
                  "SELECT BUS WEST SIDE BROADWAY-106 ST"
                ],
                "SituationRef": [
                  {
                    "SituationSimpleRef": "MTA NYCT_lmm:alert:420753"
                  }
                ],
                "Monitored": true,
                "VehicleLocation": {
                  "Longitude": -73.968278,
                  "Latitude": 40.80151
                },
                "Bearing": 337.91095,
                "ProgressRate": "normalProgress",
                "VehicleRef": "MTA NYCT_5466",
                "MonitoredCall": {
                  "AimedArrivalTime": "2025-04-01T03:17:00.388-04:00",
                  "ExpectedArrivalTime": "2025-04-01T03:21:31.119-04:00",
                  "ArrivalProximityText": "at stop",
                  "ExpectedDepartureTime": "2025-04-01T03:21:31.119-04:00",
                  "DistanceFromStop": 7,
                  "NumberOfStopsAway": 0,
                  "VisitNumber": 1,
                  "StopPointName": [
                    "W 106 ST/BROADWAY"
                  ]
                }
              },
              "RecordedAtTime": "2025-04-01T03:21:28.000-04:00"
            },
            {
              "MonitoredVehicleJourney": {
                "LineRef": "MTA NYCT_M2",
                "DirectionRef": "0",
                "FramedVehicleJourneyRef": {
                  "DataFrameRef": "2025-04-01",
                  "DatedVehicleJourneyRef": "MTA NYCT_MV_B5-Weekday-SDon-019400_M2_202"
                },
                "PublishedLineName": [
                  "M2"
                ],
                "DestinationRef": "MTA_903049",
                "DestinationName": [
                  "WASHINGTON HTS BWAY-168 ST via MADISON"
                ],
                "SituationRef": [
                  {
                    "SituationSimpleRef": "MTA NYCT_lmm:planned_work:23502"
                  },
                  {
                    "SituationSimpleRef": "MTA NYCT_lmm:alert:420753"
                  },
                  {
                    "SituationSimpleRef": "MTA NYCT_lmm:planned_work:22663"
                  }
                ],
                "Monitored": true,
                "VehicleLocation": {
                  "Longitude": -73.985471,
                  "Latitude": 40.741291
                },
                "Bearing": 53.426968,
                "ProgressRate": "normalProgress",
                "VehicleRef": "MTA NYCT_9837",
                "MonitoredCall": {
                  "AimedArrivalTime": "2025-04-01T03:19:16.414-04:00",
                  "ExpectedArrivalTime": "2025-04-01T03:21:36.373-04:00",
                  "ArrivalProximityText": "approaching",
                  "ExpectedDepartureTime": "2025-04-01T03:21:36.373-04:00",
                  "DistanceFromStop": 35,
                  "NumberOfStopsAway": 0,
                  "VisitNumber": 1,
                  "StopPointName": [
                    "E 25 ST/PARK AV SOUTH"
                  ]
                }
              },
              "RecordedAtTime": "2025-04-01T03:21:30.035-04:00"
            },
            {
              "MonitoredVehicleJourney": {
                "LineRef": "MTA NYCT_M7",
                "DirectionRef": "1",
                "FramedVehicleJourneyRef": {
                  "DataFrameRef": "2025-04-01",
                  "DatedVehicleJourneyRef": "MTA NYCT_OF_B5-Weekday-SDon-016000_M7_201"
                },
                "PublishedLineName": [
                  "M7"
                ],
                "DestinationRef": "MTA_903325",
                "DestinationName": [
                  "14 ST via COLUMBUS via 7 AV"
                ],
                "OriginAimedDepartureTime": "2025-04-01T03:40:00.000-04:00",
                "SituationRef": [
                  {
                    "SituationSimpleRef": "MTA NYCT_lmm:alert:420753"
                  }
                ],
                "Monitored": true,
                "VehicleLocation": {
                  "Longitude": -73.996177,
                  "Latitude": 40.738262
                },
                "Bearing": 53.642803,
                "ProgressRate": "noProgress",
                "ProgressStatus": [
                  "layover"
                ],
                "VehicleRef": "MTA NYCT_9584",
                "MonitoredCall": {
                  "AimedArrivalTime": "2025-04-01T03:19:00.508-04:00",
                  "ExpectedArrivalTime": "2025-04-01T03:21:33.888-04:00",
                  "ArrivalProximityText": "at stop",
                  "ExpectedDepartureTime": "2025-04-01T03:21:33.888-04:00",
                  "DistanceFromStop": 26,
                  "NumberOfStopsAway": 0,
                  "VisitNumber": 1,
                  "StopPointName": [
                    "AVENUE OF THE AMERICAS/W 16 ST"
                  ]
                }
              },
              "RecordedAtTime": "2025-04-01T03:21:27.521-04:00"
            },
            {
              "MonitoredVehicleJourney": {
                "LineRef": "MTA NYCT_M15",
                "DirectionRef": "1",
                "FramedVehicleJourneyRef": {
                  "DataFrameRef": "2025-04-01",
                  "DatedVehicleJourneyRef": "MTA NYCT_OH_B5-Weekday-SDon-018000_M15_203"
                },
                "PublishedLineName": [
                  "M15"
                ],
                "DestinationRef": "MTA_803002",
                "DestinationName": [
                  "SOUTH FERRY via 2 AV"
                ],
                "SituationRef": [
                  {
                    "SituationSimpleRef": "MTA NYCT_lmm:planned_work:10129"
                  },
                  {
                    "SituationSimpleRef": "MTA NYCT_lmm:planned_work:21502"
                  },
                  {
                    "SituationSimpleRef": "MTA NYCT_lmm:alert:420753"
                  }
                ],
                "Monitored": true,
                "VehicleLocation": {
                  "Longitude": -73.961874,
                  "Latitude": 40.763973
                },
                "Bearing": 234.02762,
                "ProgressRate": "normalProgress",
                "VehicleRef": "MTA NYCT_5969",
                "MonitoredCall": {
                  "AimedArrivalTime": "2025-04-01T03:16:53.593-04:00",
                  "ExpectedArrivalTime": "2025-04-01T03:21:35.407-04:00",
                  "ArrivalProximityText": "approaching",
                  "ExpectedDepartureTime": "2025-04-01T03:21:35.407-04:00",
                  "DistanceFromStop": 66,
                  "NumberOfStopsAway": 0,
                  "VisitNumber": 1,
                  "StopPointName": [
                    "2 AV/E 64 ST"
                  ]
                }
              },
              "RecordedAtTime": "2025-04-01T03:21:27.000-04:00"
            },
            {
              "MonitoredVehicleJourney": {
                "LineRef": "MTA NYCT_M102",
                "DirectionRef": "1",
                "FramedVehicleJourneyRef": {
                  "DataFrameRef": "2025-04-01",
                  "DatedVehicleJourneyRef": "MTA NYCT_OH_B5-Weekday-SDon-018600_M101_5"
                },
                "PublishedLineName": [
                  "M102"
                ],
                "DestinationRef": "MTA_404092",
                "DestinationName": [
                  "EAST VILLAGE 6 ST via LEX AV"
                ],
                "SituationRef": [
                  {
                    "SituationSimpleRef": "MTA NYCT_lmm:planned_work:23451"
                  },
                  {
                    "SituationSimpleRef": "MTA NYCT_lmm:planned_work:21837"
                  },
                  {
                    "SituationSimpleRef": "MTA NYCT_lmm:alert:420753"
                  }
                ],
                "Monitored": true,
                "VehicleLocation": {
                  "Longitude": -73.945399,
                  "Latitude": 40.800211
                },
                "Bearing": 337.4054,
                "ProgressRate": "normalProgress",
                "VehicleRef": "MTA NYCT_5957",
                "MonitoredCall": {
                  "AimedArrivalTime": "2025-04-01T03:18:45.608-04:00",
                  "ExpectedArrivalTime": "2025-04-01T03:21:51.981-04:00",
                  "ArrivalProximityText": "approaching",
                  "ExpectedDepartureTime": "2025-04-01T03:21:51.981-04:00",
                  "DistanceFromStop": 100,
                  "NumberOfStopsAway": 0,
                  "VisitNumber": 1,
                  "StopPointName": [
                    "E 116 ST/MADISON AV"
                  ]
                }
              },
              "RecordedAtTime": "2025-04-01T03:21:18.000-04:00"
            },
            {
              "MonitoredVehicleJourney": {
                "LineRef": "MTA NYCT_M102",
                "DirectionRef": "0",
                "FramedVehicleJourneyRef": {
                  "DataFrameRef": "2025-04-01",
                  "DatedVehicleJourneyRef": "MTA NYCT_OH_B5-Weekday-SDon-019200_M101_4"
                },
                "PublishedLineName": [
                  "M102"
                ],
                "DestinationRef": "MTA_803024",
                "DestinationName": [
                  "HARLEM 147 ST via 3 AV via LENOX AV"
                ],
                "SituationRef": [
                  {
                    "SituationSimpleRef": "MTA NYCT_lmm:planned_work:23451"
                  },
                  {
                    "SituationSimpleRef": "MTA NYCT_lmm:planned_work:21837"
                  },
                  {
                    "SituationSimpleRef": "MTA NYCT_lmm:alert:420753"
                  }
                ],
                "Monitored": true,
                "VehicleLocation": {
                  "Longitude": -73.96676,
                  "Latitude": 40.761299
                },
                "Bearing": 54.462322,
                "ProgressRate": "normalProgress",
                "VehicleRef": "MTA NYCT_5927",
                "MonitoredCall": {
                  "AimedArrivalTime": "2025-04-01T03:23:35.716-04:00",
                  "ExpectedArrivalTime": "2025-04-01T03:21:32.722-04:00",
                  "ArrivalProximityText": "< 1 stop away",
                  "ExpectedDepartureTime": "2025-04-01T03:21:32.722-04:00",
                  "DistanceFromStop": 164,
                  "NumberOfStopsAway": 0,
                  "VisitNumber": 1,
                  "StopPointName": [
                    "3 AV/E 60 ST"
                  ]
                }
              },
              "RecordedAtTime": "2025-04-01T03:21:14.000-04:00"
            },
            {
              "MonitoredVehicleJourney": {
                "LineRef": "MTA NYCT_M96",
                "DirectionRef": "1",
                "FramedVehicleJourneyRef": {
                  "DataFrameRef": "2025-04-01",
                  "DatedVehicleJourneyRef": "MTA NYCT_MV_B5-Weekday-SDon-020000_M96_801"
                },
                "PublishedLineName": [
                  "M96"
                ],
                "DestinationRef": "MTA_903004",
                "DestinationName": [
                  "WEST SIDE WEST END AV CROSSTOWN"
                ],
                "SituationRef": [
                  {
                    "SituationSimpleRef": "MTA NYCT_lmm:alert:420753"
                  }
                ],
                "Monitored": true,
                "VehicleLocation": {
                  "Longitude": -73.946873,
                  "Latitude": 40.784536
                },
                "Bearing": 233.67317,
                "ProgressRate": "normalProgress",
                "VehicleRef": "MTA NYCT_9686",
                "MonitoredCall": {
                  "AimedArrivalTime": "2025-04-01T03:21:22.773-04:00",
                  "ExpectedArrivalTime": "2025-04-01T03:21:31.119-04:00",
                  "ArrivalProximityText": "approaching",
                  "ExpectedDepartureTime": "2025-04-01T03:21:31.119-04:00",
                  "DistanceFromStop": 52,
                  "NumberOfStopsAway": 0,
                  "Extensions": {
                    "Capacities": {
                      "EstimatedPassengerCount": 2,
                      "EstimatedPassengerCapacity": 80
                    }
                  },
                  "VisitNumber": 1,
                  "StopPointName": [
                    "E 96 ST/2 AV"
                  ]
                }
              },
              "RecordedAtTime": "2025-04-01T03:21:14.580-04:00"
            },
            {
              "MonitoredVehicleJourney": {
                "LineRef": "MTA NYCT_M125",
                "DirectionRef": "0",
                "FramedVehicleJourneyRef": {
                  "DataFrameRef": "2025-04-01",
                  "DatedVehicleJourneyRef": "MTA NYCT_OF_B5-Weekday-SDon-018000_M125_501"
                },
                "PublishedLineName": [
                  "M125"
                ],
                "DestinationRef": "MTA_103772",
                "DestinationName": [
                  "THE HUB 3 AV/149 ST via 125 ST"
                ],
                "OriginAimedDepartureTime": "2025-04-01T03:30:00.000-04:00",
                "SituationRef": [
                  {
                    "SituationSimpleRef": "MTA NYCT_lmm:alert:420753"
                  }
                ],
                "Monitored": true,
                "VehicleLocation": {
                  "Longitude": -73.916339,
                  "Latitude": 40.815939
                },
                "Bearing": 31.89079,
                "ProgressRate": "noProgress",
                "ProgressStatus": [
                  "layover"
                ],
                "VehicleRef": "MTA NYCT_5264",
                "MonitoredCall": {
                  "AimedArrivalTime": "2025-04-01T03:23:00.853-04:00",
                  "ExpectedArrivalTime": "2025-04-01T03:21:40.780-04:00",
                  "ArrivalProximityText": "approaching",
                  "ExpectedDepartureTime": "2025-04-01T03:21:40.780-04:00",
                  "DistanceFromStop": 51,
                  "NumberOfStopsAway": 0,
                  "VisitNumber": 1,
                  "StopPointName": [
                    "BERGEN AV/WESTCHESTER AV"
                  ]
                }
              },
              "RecordedAtTime": "2025-04-01T03:21:28.000-04:00"
            },
            {
              "MonitoredVehicleJourney": {
                "LineRef": "MTA NYCT_M104",
                "DirectionRef": "1",
                "FramedVehicleJourneyRef": {
                  "DataFrameRef": "2025-04-01",
                  "DatedVehicleJourneyRef": "MTA NYCT_MV_B5-Weekday-SDon-020000_M104_102"
                },
                "PublishedLineName": [
                  "M104"
                ],
                "DestinationRef": "MTA_404153",
                "DestinationName": [
                  "41 ST via BROADWAY/7 AV"
                ],
                "SituationRef": [
                  {
                    "SituationSimpleRef": "MTA NYCT_lmm:planned_work:15147"
                  },
                  {
                    "SituationSimpleRef": "MTA NYCT_lmm:alert:420753"
                  }
                ],
                "Monitored": true,
                "VehicleLocation": {
                  "Longitude": -73.956422,
                  "Latitude": 40.813541
                },
                "Bearing": 131.04767,
                "ProgressRate": "normalProgress",
                "VehicleRef": "MTA NYCT_9455",
                "MonitoredCall": {
                  "AimedArrivalTime": "2025-04-01T03:22:38.066-04:00",
                  "ExpectedArrivalTime": "2025-04-01T03:21:31.119-04:00",
                  "ArrivalProximityText": "at stop",
                  "ExpectedDepartureTime": "2025-04-01T03:21:31.119-04:00",
                  "DistanceFromStop": 12,
                  "NumberOfStopsAway": 0,
                  "VisitNumber": 1,
                  "StopPointName": [
                    "W 125 ST/AMSTERDAM AV"
                  ]
                }
              },
              "RecordedAtTime": "2025-04-01T03:21:13.000-04:00"
            },
            {
              "MonitoredVehicleJourney": {
                "LineRef": "MTA NYCT_M104",
                "DirectionRef": "0",
                "FramedVehicleJourneyRef": {
                  "DataFrameRef": "2025-04-01",
                  "DatedVehicleJourneyRef": "MTA NYCT_MV_B5-Weekday-SDon-020000_M104_101"
                },
                "PublishedLineName": [
                  "M104"
                ],
                "DestinationRef": "MTA_903352",
                "DestinationName": [
                  "WEST HARLEM 129 ST via BROADWAY"
                ],
                "SituationRef": [
                  {
                    "SituationSimpleRef": "MTA NYCT_lmm:planned_work:15147"
                  },
                  {
                    "SituationSimpleRef": "MTA NYCT_lmm:alert:420753"
                  }
                ],
                "Monitored": true,
                "VehicleLocation": {
                  "Longitude": -73.98303,
                  "Latitude": 40.766416
                },
                "Bearing": 52.696053,
                "ProgressRate": "normalProgress",
                "VehicleRef": "MTA NYCT_9440",
                "MonitoredCall": {
                  "AimedArrivalTime": "2025-04-01T03:24:19.072-04:00",
                  "ExpectedArrivalTime": "2025-04-01T03:22:05.934-04:00",
                  "ArrivalProximityText": "< 1 stop away",
                  "ExpectedDepartureTime": "2025-04-01T03:22:05.934-04:00",
                  "DistanceFromStop": 439,
                  "NumberOfStopsAway": 0,
                  "VisitNumber": 1,
                  "StopPointName": [
                    "BROADWAY/W 61 ST"
                  ]
                }
              },
              "RecordedAtTime": "2025-04-01T03:21:11.069-04:00"
            },
            {
              "MonitoredVehicleJourney": {
                "LineRef": "MTA NYCT_M101",
                "DirectionRef": "1",
                "FramedVehicleJourneyRef": {
                  "DataFrameRef": "2025-04-01",
                  "DatedVehicleJourneyRef": "MTA NYCT_OH_B5-Weekday-SDon-019000_M101_6"
                },
                "PublishedLineName": [
                  "M101"
                ],
                "DestinationRef": "MTA_404092",
                "DestinationName": [
                  "EAST VILLAGE 3 AV-6 ST via LEX AV"
                ],
                "SituationRef": [
                  {
                    "SituationSimpleRef": "MTA NYCT_lmm:planned_work:23451"
                  },
                  {
                    "SituationSimpleRef": "MTA NYCT_lmm:planned_work:21837"
                  },
                  {
                    "SituationSimpleRef": "MTA NYCT_lmm:alert:420753"
                  }
                ],
                "Monitored": true,
                "VehicleLocation": {
                  "Longitude": -73.942339,
                  "Latitude": 40.832462
                },
                "Bearing": 232.25319,
                "ProgressRate": "normalProgress",
                "VehicleRef": "MTA NYCT_5866",
                "MonitoredCall": {
                  "AimedArrivalTime": "2025-04-01T03:22:22.239-04:00",
                  "ExpectedArrivalTime": "2025-04-01T03:21:31.119-04:00",
                  "ArrivalProximityText": "approaching",
                  "ExpectedDepartureTime": "2025-04-01T03:21:31.119-04:00",
                  "DistanceFromStop": 70,
                  "NumberOfStopsAway": 0,
                  "VisitNumber": 1,
                  "StopPointName": [
                    "AMSTERDAM AV/W 156 ST"
                  ]
                }
              },
              "RecordedAtTime": "2025-04-01T03:21:08.000-04:00"
            },
            {
              "MonitoredVehicleJourney": {
                "LineRef": "MTA NYCT_M103",
                "DirectionRef": "0",
                "FramedVehicleJourneyRef": {
                  "DataFrameRef": "2025-04-01",
                  "DatedVehicleJourneyRef": "MTA NYCT_OH_B5-Weekday-SDon-016200_M101_1"
                },
                "PublishedLineName": [
                  "M103"
                ],
                "DestinationRef": "MTA_903042",
                "DestinationName": [
                  "EAST HARLEM 125 ST via 3 AV"
                ],
                "OriginAimedDepartureTime": "2025-04-01T04:21:00.000-04:00",
                "SituationRef": [
                  {
                    "SituationSimpleRef": "MTA NYCT_lmm:planned_work:23451"
                  },
                  {
                    "SituationSimpleRef": "MTA NYCT_lmm:planned_work:21837"
                  },
                  {
                    "SituationSimpleRef": "MTA NYCT_lmm:alert:420753"
                  }
                ],
                "Monitored": true,
                "VehicleLocation": {
                  "Longitude": -73.935588,
                  "Latitude": 40.804
                },
                "Bearing": 54.310932,
                "ProgressRate": "noProgress",
                "ProgressStatus": [
                  "layover"
                ],
                "VehicleRef": "MTA NYCT_5809",
                "MonitoredCall": {
                  "AimedArrivalTime": "2025-04-01T03:19:00.331-04:00",
                  "ExpectedArrivalTime": "2025-04-01T03:21:31.119-04:00",
                  "ArrivalProximityText": "at stop",
                  "ExpectedDepartureTime": "2025-04-01T03:21:31.119-04:00",
                  "DistanceFromStop": 28,
                  "NumberOfStopsAway": 0,
                  "VisitNumber": 1,
                  "StopPointName": [
                    "3 AV /E 125 ST"
                  ]
                }
              },
              "RecordedAtTime": "2025-04-01T03:21:24.000-04:00"
            },
            {
              "MonitoredVehicleJourney": {
                "LineRef": "MTA NYCT_M15",
                "DirectionRef": "0",
                "FramedVehicleJourneyRef": {
                  "DataFrameRef": "2025-04-01",
                  "DatedVehicleJourneyRef": "MTA NYCT_OH_B5-Weekday-SDon-018000_M15_201"
                },
                "PublishedLineName": [
                  "M15"
                ],
                "DestinationRef": "MTA_803054",
                "DestinationName": [
                  "EAST HARLEM 125 ST via 1 AV"
                ],
                "SituationRef": [
                  {
                    "SituationSimpleRef": "MTA NYCT_lmm:planned_work:10129"
                  },
                  {
                    "SituationSimpleRef": "MTA NYCT_lmm:planned_work:21502"
                  },
                  {
                    "SituationSimpleRef": "MTA NYCT_lmm:alert:420753"
                  }
                ],
                "Monitored": true,
                "VehicleLocation": {
                  "Longitude": -73.97996,
                  "Latitude": 40.73493
                },
                "Bearing": 53.130104,
                "ProgressRate": "normalProgress",
                "VehicleRef": "MTA NYCT_5827",
                "MonitoredCall": {
                  "AimedArrivalTime": "2025-04-01T03:18:13.352-04:00",
                  "ExpectedArrivalTime": "2025-04-01T03:21:31.119-04:00",
                  "ArrivalProximityText": "at stop",
                  "ExpectedDepartureTime": "2025-04-01T03:21:31.119-04:00",
                  "DistanceFromStop": 25,
                  "NumberOfStopsAway": 0,
                  "VisitNumber": 1,
                  "StopPointName": [
                    "1 AV/E 20 ST"
                  ]
                }
              },
              "RecordedAtTime": "2025-04-01T03:21:25.000-04:00"
            },
            {
              "MonitoredVehicleJourney": {
                "LineRef": "MTA NYCT_M103",
                "DirectionRef": "0",
                "FramedVehicleJourneyRef": {
                  "DataFrameRef": "2025-04-01",
                  "DatedVehicleJourneyRef": "MTA NYCT_OH_B5-Weekday-SDon-016200_M101_1"
                },
                "PublishedLineName": [
                  "M103"
                ],
                "DestinationRef": "MTA_903042",
                "DestinationName": [
                  "EAST HARLEM 125 ST via 3 AV"
                ],
                "OriginAimedDepartureTime": "2025-04-01T04:21:00.000-04:00",
                "SituationRef": [
                  {
                    "SituationSimpleRef": "MTA NYCT_lmm:planned_work:23451"
                  },
                  {
                    "SituationSimpleRef": "MTA NYCT_lmm:planned_work:21837"
                  },
                  {
                    "SituationSimpleRef": "MTA NYCT_lmm:alert:420753"
                  }
                ],
                "Monitored": true,
                "VehicleLocation": {
                  "Longitude": -73.935424,
                  "Latitude": 40.804228
                },
                "Bearing": 54.310932,
                "ProgressRate": "noProgress",
                "ProgressStatus": [
                  "layover"
                ],
                "VehicleRef": "MTA NYCT_5815",
                "MonitoredCall": {
                  "AimedArrivalTime": "2025-04-01T03:19:00.377-04:00",
                  "ArrivalProximityText": "at stop",
                  "DistanceFromStop": 0,
                  "NumberOfStopsAway": 0,
                  "VisitNumber": 1,
                  "StopPointName": [
                    "3 AV /E 125 ST"
                  ]
                }
              },
              "RecordedAtTime": "2025-04-01T03:21:27.000-04:00"
            },
            {
              "MonitoredVehicleJourney": {
                "LineRef": "MTA NYCT_M14A+",
                "DirectionRef": "0",
                "FramedVehicleJourneyRef": {
                  "DataFrameRef": "2025-04-01",
                  "DatedVehicleJourneyRef": "MTA NYCT_MQ_B5-Weekday-SDon-018400_SBS14_702"
                },
                "PublishedLineName": [
                  "M14A-SBS"
                ],
                "DestinationRef": "MTA_903025",
                "DestinationName": [
                  "SELECT BUS LES GRAND-FDR via 14 ST"
                ],
                "SituationRef": [
                  {
                    "SituationSimpleRef": "MTA NYCT_lmm:alert:420753"
                  }
                ],
                "Monitored": true,
                "VehicleLocation": {
                  "Longitude": -73.986978,
                  "Latitude": 40.720916
                },
                "Bearing": 242.84021,
                "ProgressRate": "normalProgress",
                "VehicleRef": "MTA NYCT_5599",
                "MonitoredCall": {
                  "AimedArrivalTime": "2025-04-01T03:18:00.547-04:00",
                  "ExpectedArrivalTime": "2025-04-01T03:22:27.698-04:00",
                  "ArrivalProximityText": "< 1 stop away",
                  "ExpectedDepartureTime": "2025-04-01T03:22:27.698-04:00",
                  "DistanceFromStop": 322,
                  "NumberOfStopsAway": 0,
                  "VisitNumber": 1,
                  "StopPointName": [
                    "ESSEX ST/DELANCEY ST"
                  ]
                }
              },
              "RecordedAtTime": "2025-04-01T03:21:15.000-04:00"
            },
            {
              "MonitoredVehicleJourney": {
                "LineRef": "MTA NYCT_M79+",
                "DirectionRef": "0",
                "FramedVehicleJourneyRef": {
                  "DataFrameRef": "2025-04-01",
                  "DatedVehicleJourneyRef": "MTA NYCT_MQ_B5-Weekday-SDon-019500_SB79_651"
                },
                "PublishedLineName": [
                  "M79-SBS"
                ],
                "DestinationRef": "MTA_401878",
                "DestinationName": [
                  "SELECT BUS YRKVLLE EAST END AV CROSSTOWN"
                ],
                "SituationRef": [
                  {
                    "SituationSimpleRef": "MTA NYCT_lmm:planned_work:18087"
                  },
                  {
                    "SituationSimpleRef": "MTA NYCT_lmm:alert:420753"
                  }
                ],
                "Monitored": true,
                "VehicleLocation": {
                  "Longitude": -73.976382,
                  "Latitude": 40.784043
                },
                "Bearing": 337.29364,
                "ProgressRate": "normalProgress",
                "VehicleRef": "MTA NYCT_5598",
                "MonitoredCall": {
                  "AimedArrivalTime": "2025-04-01T03:19:26.552-04:00",
                  "ExpectedArrivalTime": "2025-04-01T03:22:21.399-04:00",
                  "ArrivalProximityText": "< 1 stop away",
                  "ExpectedDepartureTime": "2025-04-01T03:22:21.399-04:00",
                  "DistanceFromStop": 219,
                  "NumberOfStopsAway": 0,
                  "VisitNumber": 1,
                  "StopPointName": [
                    "W 81 ST/COLUMBUS AV"
                  ]
                }
              },
              "RecordedAtTime": "2025-04-01T03:21:19.000-04:00"
            },
            {
              "MonitoredVehicleJourney": {
                "LineRef": "MTA NYCT_M86+",
                "DirectionRef": "1",
                "FramedVehicleJourneyRef": {
                  "DataFrameRef": "2025-04-01",
                  "DatedVehicleJourneyRef": "MTA NYCT_MQ_B5-Weekday-SDon-020000_SBS86_951"
                },
                "PublishedLineName": [
                  "M86-SBS"
                ],
                "DestinationRef": "MTA_403518",
                "DestinationName": [
                  "SELECT BUS WESTSIDE WEST END AV CROSSTWN"
                ],
                "SituationRef": [
                  {
                    "SituationSimpleRef": "MTA NYCT_lmm:alert:420753"
                  }
                ],
                "Monitored": true,
                "VehicleLocation": {
                  "Longitude": -73.945532,
                  "Latitude": 40.778091
                },
                "Bearing": 233.42697,
                "ProgressRate": "normalProgress",
                "VehicleRef": "MTA NYCT_5513",
                "MonitoredCall": {
                  "AimedArrivalTime": "2025-04-01T03:22:07.665-04:00",
                  "ExpectedArrivalTime": "2025-04-01T03:21:48.996-04:00",
                  "ArrivalProximityText": "< 1 stop away",
                  "ExpectedDepartureTime": "2025-04-01T03:21:48.996-04:00",
                  "DistanceFromStop": 244,
                  "NumberOfStopsAway": 0,
                  "VisitNumber": 1,
                  "StopPointName": [
                    "YORK AV/E 87 ST"
                  ]
                }
              },
              "RecordedAtTime": "2025-04-01T03:21:26.000-04:00"
            },
            {
              "MonitoredVehicleJourney": {
                "LineRef": "MTA NYCT_M23+",
                "DirectionRef": "1",
                "FramedVehicleJourneyRef": {
                  "DataFrameRef": "2025-04-01",
                  "DatedVehicleJourneyRef": "MTA NYCT_MQ_B5-Weekday-SDon-018000_SBS23_801"
                },
                "PublishedLineName": [
                  "M23-SBS"
                ],
                "DestinationRef": "MTA_404085",
                "DestinationName": [
                  "SELECT BUS CHELSEA PIERS 12AV CROSSTOWN"
                ],
                "SituationRef": [
                  {
                    "SituationSimpleRef": "MTA NYCT_lmm:alert:420753"
                  }
                ],
                "Monitored": true,
                "VehicleLocation": {
                  "Longitude": -74.007952,
                  "Latitude": 40.748971
                },
                "Bearing": 298.264,
                "ProgressRate": "normalProgress",
                "VehicleRef": "MTA NYCT_5518",
                "MonitoredCall": {
                  "AimedArrivalTime": "2025-04-01T03:15:00.672-04:00",
                  "ExpectedArrivalTime": "2025-04-01T03:21:31.119-04:00",
                  "ArrivalProximityText": "at stop",
                  "ExpectedDepartureTime": "2025-04-01T03:21:31.119-04:00",
                  "DistanceFromStop": 7,
                  "NumberOfStopsAway": 0,
                  "VisitNumber": 1,
                  "StopPointName": [
                    "12 AV/W 23 ST"
                  ]
                }
              },
              "RecordedAtTime": "2025-04-01T03:21:14.000-04:00"
            },
            {
              "MonitoredVehicleJourney": {
                "LineRef": "MTA NYCT_M14D+",
                "DirectionRef": "1",
                "FramedVehicleJourneyRef": {
                  "DataFrameRef": "2025-04-01",
                  "DatedVehicleJourneyRef": "MTA NYCT_MQ_B5-Weekday-SDon-018100_SBS14_701"
                },
                "PublishedLineName": [
                  "M14D-SBS"
                ],
                "DestinationRef": "MTA_903358",
                "DestinationName": [
                  "SELECT BUS CHLSEA PIERS  11 AV via 14 ST"
                ],
                "OriginAimedDepartureTime": "2025-04-01T03:32:00.000-04:00",
                "SituationRef": [
                  {
                    "SituationSimpleRef": "MTA NYCT_lmm:planned_work:9387"
                  },
                  {
                    "SituationSimpleRef": "MTA NYCT_lmm:planned_work:22448"
                  },
                  {
                    "SituationSimpleRef": "MTA NYCT_lmm:alert:420753"
                  }
                ],
                "Monitored": true,
                "VehicleLocation": {
                  "Longitude": -74.00664,
                  "Latitude": 40.744296
                },
                "Bearing": 53.735985,
                "ProgressRate": "noProgress",
                "ProgressStatus": [
                  "layover"
                ],
                "VehicleRef": "MTA NYCT_6188",
                "MonitoredCall": {
                  "AimedArrivalTime": "2025-04-01T03:22:00.735-04:00",
                  "ArrivalProximityText": "at stop",
                  "DistanceFromStop": 0,
                  "NumberOfStopsAway": 0,
                  "Extensions": {
                    "Capacities": {
                      "EstimatedPassengerCount": 1,
                      "EstimatedPassengerCapacity": 80
                    }
                  },
                  "VisitNumber": 1,
                  "StopPointName": [
                    "10 AV/W 18 ST"
                  ]
                }
              },
              "RecordedAtTime": "2025-04-01T03:21:16.000-04:00"
            }
          ]
        }
      ]
    }
  }
}